{"v":"5.11.0","fr":60,"ip":0,"op":180,"w":500,"h":500,"nm":"18-Explosion","ddd":0,"assets":[{"id":"comp_0","nm":"explosion","fr":60,"layers":[{"ddd":0,"ind":1,"ty":1,"nm":"Main Stroke width - Color Ctrl","sr":1,"ks":{"o":{"a":0,"k":0,"ix":11},"r":{"a":0,"k":0,"ix":10},"p":{"a":0,"k":[250,250,0],"ix":2,"l":2},"a":{"a":0,"k":[50,50,0],"ix":1,"l":2},"s":{"a":0,"k":[100,100,100],"ix":6,"l":2}},"ao":0,"ef":[{"ty":5,"nm":"Stroke width","np":3,"mn":"ADBE Slider Control","ix":1,"en":1,"ef":[{"ty":0,"nm":"Slider","mn":"ADBE Slider Control-0001","ix":1,"v":{"a":0,"k":16,"ix":1}}]},{"ty":5,"nm":"Base Color","np":3,"mn":"ADBE Color Control","ix":2,"en":1,"ef":[{"ty":2,"nm":"Color","mn":"ADBE Color Control-0001","ix":1,"v":{"a":0,"k":[0.019607843831,0.164705887437,0.458823531866,1],"ix":1,"x":"var $bm_rt;\n$bm_rt = effect('Base Color')('Color');"}}]},{"ty":5,"nm":"Highlight","np":3,"mn":"ADBE Color Control","ix":3,"en":1,"ef":[{"ty":2,"nm":"Color","mn":"ADBE Color Control-0001","ix":1,"v":{"a":0,"k":[0.992156863213,0.560784339905,0.003921568859,1],"ix":1}}]},{"ty":5,"nm":"Stroke width 2","np":3,"mn":"ADBE Slider Control","ix":4,"en":1,"ef":[{"ty":0,"nm":"Slider","mn":"ADBE Slider Control-0001","ix":1,"v":{"a":0,"k":18,"ix":1}}]}],"sw":100,"sh":100,"sc":"#ffffff","ip":0,"op":185,"st":0,"bm":0},{"ddd":0,"ind":2,"ty":3,"nm":"NULL","sr":1,"ks":{"o":{"a":0,"k":0,"ix":11},"r":{"a":0,"k":0,"ix":10},"p":{"a":1,"k":[{"i":{"x":0.667,"y":1},"o":{"x":0.333,"y":0},"t":36,"s":[250,250,0],"to":[0,0,0],"ti":[0,0,0]},{"i":{"x":0.667,"y":1},"o":{"x":0.333,"y":0},"t":98,"s":[250,306,0],"to":[0,0,0],"ti":[0,0,0]},{"t":147,"s":[250,250,0]}],"ix":2,"l":2},"a":{"a":0,"k":[60,60,0],"ix":1,"l":2},"s":{"a":0,"k":[100,100,100],"ix":6,"l":2}},"ao":0,"ip":0,"op":180,"st":0,"bm":0},{"ddd":0,"ind":3,"ty":4,"nm":"small cloud 2","td":1,"sr":1,"ks":{"o":{"a":0,"k":100,"ix":11},"r":{"a":0,"k":0,"ix":10},"p":{"a":0,"k":[250,384.768,0],"ix":2,"l":2},"a":{"a":0,"k":[0,0,0],"ix":1,"l":2},"s":{"a":0,"k":[100,100,100],"ix":6,"l":2}},"ao":0,"shapes":[{"ty":"gr","it":[{"ty":"gr","it":[{"ind":0,"ty":"sh","ix":1,"ks":{"a":0,"k":{"i":[[0,0],[-9.001,-9.001],[12.648,-12.648],[0,0],[-12.648,12.648],[-11.296,-3.809]],"o":[[11.296,-3.809],[12.648,12.648],[0,0],[-12.648,-12.648],[9.001,-9.001],[0,0]],"v":[[41.877,-16.85],[73.465,-9.07],[73.465,36.732],[-73.465,36.732],[-73.465,-9.07],[-37.877,-19.288]],"c":false},"ix":2},"nm":"Path 2","mn":"ADBE Vector Shape - Group","hd":false},{"ty":"fl","c":{"a":0,"k":[1,0,0,1],"ix":4},"o":{"a":0,"k":100,"ix":5},"r":1,"bm":0,"nm":"Fill 1","mn":"ADBE Vector Graphic - Fill","hd":false},{"ty":"tr","p":{"a":0,"k":[0,0],"ix":2},"a":{"a":0,"k":[0,0],"ix":1},"s":{"a":1,"k":[{"i":{"x":[0.4,0.4],"y":[1,1]},"o":{"x":[0.333,0.333],"y":[0,0]},"t":23,"s":[100,100]},{"i":{"x":[0.4,0.4],"y":[1,1]},"o":{"x":[0.167,0.167],"y":[0,0]},"t":54,"s":[75,75]},{"i":{"x":[0.667,0.667],"y":[1,1]},"o":{"x":[0.167,0.167],"y":[0,0]},"t":101,"s":[75,75]},{"t":135,"s":[100,100]}],"ix":3},"r":{"a":0,"k":0,"ix":6},"o":{"a":0,"k":100,"ix":7},"sk":{"a":0,"k":0,"ix":4},"sa":{"a":0,"k":0,"ix":5},"nm":"Transform"}],"nm":"Group 2","np":3,"cix":2,"bm":0,"ix":1,"mn":"ADBE Vector Group","hd":false},{"ty":"gr","it":[{"ind":0,"ty":"sh","ix":1,"ks":{"a":0,"k":{"i":[[0,0],[25.238,0],[0.695,-3.95]],"o":[[-2.445,-18.7],[-25.238,0],[0,0]],"v":[[43.445,-16.568],[0,-36.732],[-37.195,-17.318]],"c":false},"ix":2},"nm":"Path 1","mn":"ADBE Vector Shape - Group","hd":false},{"ty":"fl","c":{"a":0,"k":[1,0,0,1],"ix":4},"o":{"a":0,"k":100,"ix":5},"r":1,"bm":0,"nm":"Fill 1","mn":"ADBE Vector Graphic - Fill","hd":false},{"ty":"tr","p":{"a":0,"k":[0,0],"ix":2},"a":{"a":0,"k":[0,0],"ix":1},"s":{"a":1,"k":[{"i":{"x":[0.4,0.4],"y":[1,1]},"o":{"x":[0.333,0.333],"y":[0,0]},"t":23,"s":[100,100]},{"i":{"x":[0.4,0.4],"y":[1,1]},"o":{"x":[0.167,0.167],"y":[0,0]},"t":54,"s":[75,75]},{"i":{"x":[0.667,0.667],"y":[1,1]},"o":{"x":[0.167,0.167],"y":[0,0]},"t":101,"s":[75,75]},{"t":135,"s":[100,100]}],"ix":3},"r":{"a":0,"k":0,"ix":6},"o":{"a":0,"k":100,"ix":7},"sk":{"a":0,"k":0,"ix":4},"sa":{"a":0,"k":0,"ix":5},"nm":"Transform"}],"nm":"Group 1","np":3,"cix":2,"bm":0,"ix":2,"mn":"ADBE Vector Group","hd":false},{"ty":"tr","p":{"a":0,"k":[0,0],"ix":2},"a":{"a":0,"k":[0,0],"ix":1},"s":{"a":0,"k":[100,100],"ix":3},"r":{"a":0,"k":0,"ix":6},"o":{"a":0,"k":100,"ix":7},"sk":{"a":0,"k":0,"ix":4},"sa":{"a":0,"k":0,"ix":5},"nm":"Transform"}],"nm":"small cloud","np":3,"cix":2,"bm":0,"ix":1,"mn":"ADBE Vector Group","hd":false}],"ip":0,"op":180,"st":0,"ct":1,"bm":0},{"ddd":0,"ind":4,"ty":4,"nm":"big cloud","tt":2,"tp":3,"sr":1,"ks":{"o":{"a":0,"k":100,"ix":11},"r":{"a":0,"k":0,"ix":10},"p":{"a":0,"k":[250,164.294,0],"ix":2,"l":2},"a":{"a":0,"k":[0,0,0],"ix":1,"l":2},"s":{"a":0,"k":[100,100,100],"ix":6,"l":2}},"ao":0,"shapes":[{"ty":"gr","it":[{"ty":"rc","d":1,"s":{"a":0,"k":[428,320],"ix":2},"p":{"a":0,"k":[0,0],"ix":3},"r":{"a":0,"k":0,"ix":4},"nm":"Rectangle Path 1","mn":"ADBE Vector Shape - Rect","hd":false},{"ty":"fl","c":{"a":0,"k":[0.992156862745,0.376470588235,0.313725490196,1],"ix":4},"o":{"a":0,"k":100,"ix":5},"r":1,"bm":0,"nm":"Fill 1","mn":"ADBE Vector Graphic - Fill","hd":false},{"ty":"tr","p":{"a":0,"k":[-2,-5.294],"ix":2},"a":{"a":0,"k":[0,0],"ix":1},"s":{"a":0,"k":[100,100],"ix":3},"r":{"a":0,"k":0,"ix":6},"o":{"a":0,"k":0,"ix":7},"sk":{"a":0,"k":0,"ix":4},"sa":{"a":0,"k":0,"ix":5},"nm":"Transform"}],"nm":"Rectangle 1","np":3,"cix":2,"bm":0,"ix":1,"mn":"ADBE Vector Group","hd":false},{"ty":"gr","it":[{"ty":"gr","it":[{"ind":0,"ty":"sh","ix":1,"ks":{"a":0,"k":{"i":[[0,0],[13.323,13.323],[13.404,-11.325]],"o":[[13.323,-13.323],[-12.633,-12.633],[0,0]],"v":[[103.288,-2.962],[103.288,-51.209],[57.174,-53.171]],"c":false},"ix":2},"nm":"Path 1","mn":"ADBE Vector Shape - Group","hd":false},{"ind":1,"ty":"sh","ix":2,"ks":{"a":0,"k":{"i":[[0,0],[12.637,-12.637],[-13.323,-13.323]],"o":[[-13.404,-11.337],[-13.323,13.323],[0,0]],"v":[[-57.161,-53.16],[-103.288,-51.209],[-103.288,-2.962]],"c":false},"ix":2},"nm":"Path 2","mn":"ADBE Vector Shape - Group","hd":false},{"ind":2,"ty":"sh","ix":3,"ks":{"a":0,"k":{"i":[[0,0],[32.812,0],[5.345,-31.288]],"o":[[-5.345,-31.288],[-32.812,0],[0,0]],"v":[[65.402,-30.69],[0,-85.794],[-65.402,-30.69]],"c":false},"ix":2},"nm":"Path 3","mn":"ADBE Vector Shape - Group","hd":false},{"ind":3,"ty":"sh","ix":4,"ks":{"a":0,"k":{"i":[[0,0],[-29.3,0],[-10.477,25.524]],"o":[[10.477,25.524],[29.3,0],[0,0]],"v":[[-64.868,42.289],[0,85.794],[64.868,42.289]],"c":false},"ix":2},"nm":"Path 4","mn":"ADBE Vector Shape - Group","hd":false},{"ind":4,"ty":"sh","ix":5,"ks":{"a":0,"k":{"i":[[0,0],[0,-21.139],[-30.765,0],[-10.125,10.447]],"o":[[-17.349,9.438],[0,30.765],[15.698,0],[0,0]],"v":[[-112.281,-18.876],[-141.405,30.089],[-85.699,85.794],[-45.706,68.845]],"c":false},"ix":2},"nm":"Path 5","mn":"ADBE Vector Shape - Group","hd":false},{"ind":5,"ty":"sh","ix":6,"ks":{"a":0,"k":{"i":[[0,0],[0,-21.139],[30.765,0],[10.125,10.447]],"o":[[17.349,9.438],[0,30.765],[-15.698,0],[0,0]],"v":[[112.281,-18.876],[141.405,30.089],[85.699,85.794],[45.706,68.845]],"c":false},"ix":2},"nm":"Path 6","mn":"ADBE Vector Shape - Group","hd":false},{"ty":"tr","p":{"a":0,"k":[0,0],"ix":2},"a":{"a":0,"k":[0,0],"ix":1},"s":{"a":1,"k":[{"i":{"x":[0.4,0.4],"y":[1,1]},"o":{"x":[0.333,0.333],"y":[0,0]},"t":24,"s":[100,100]},{"i":{"x":[0.13,0.13],"y":[1,1]},"o":{"x":[0.167,0.167],"y":[0,0]},"t":54,"s":[30,30]},{"i":{"x":[0.13,0.13],"y":[1,1]},"o":{"x":[0.07,0.07],"y":[0,0]},"t":101,"s":[30,30]},{"t":144,"s":[100,100]}],"ix":3},"r":{"a":0,"k":0,"ix":6},"o":{"a":0,"k":100,"ix":7},"sk":{"a":0,"k":0,"ix":4},"sa":{"a":0,"k":0,"ix":5},"nm":"Transform"}],"nm":"Group 1","np":6,"cix":2,"bm":0,"ix":1,"mn":"ADBE Vector Group","hd":false},{"ty":"st","c":{"a":0,"k":[0,0,0,1],"ix":3,"x":"var $bm_rt;\n$bm_rt = thisComp.layer('Main Stroke width - Color Ctrl').effect('Base Color')('Color');"},"o":{"a":0,"k":100,"ix":4},"w":{"a":0,"k":16,"ix":5,"x":"var $bm_rt;\n$bm_rt = thisComp.layer('Main Stroke width - Color Ctrl').effect('Stroke width')('Slider');"},"lc":2,"lj":2,"bm":0,"nm":"Stroke 1","mn":"ADBE Vector Graphic - Stroke","hd":false},{"ty":"tr","p":{"a":1,"k":[{"i":{"x":0.4,"y":1},"o":{"x":0.333,"y":0},"t":24,"s":[0,0],"to":[0,0],"ti":[0,0]},{"i":{"x":0.13,"y":0.13},"o":{"x":0.167,"y":0.167},"t":54,"s":[0,221],"to":[0,0],"ti":[0,0]},{"i":{"x":0.13,"y":1},"o":{"x":0.07,"y":0},"t":101,"s":[0,221],"to":[0,0],"ti":[0,0]},{"t":144,"s":[0,0]}],"ix":2},"a":{"a":0,"k":[0,0],"ix":1},"s":{"a":0,"k":[100,100],"ix":3},"r":{"a":0,"k":0,"ix":6},"o":{"a":0,"k":100,"ix":7},"sk":{"a":0,"k":0,"ix":4},"sa":{"a":0,"k":0,"ix":5},"nm":"Transform"}],"nm":"big cloud","np":2,"cix":2,"bm":0,"ix":2,"mn":"ADBE Vector Group","hd":false}],"ip":0,"op":180,"st":0,"ct":1,"bm":0},{"ddd":0,"ind":5,"ty":4,"nm":"big","sr":1,"ks":{"o":{"a":0,"k":100,"ix":11},"r":{"a":0,"k":0,"ix":10},"p":{"a":1,"k":[{"i":{"x":0.775,"y":0.508},"o":{"x":0.494,"y":0},"t":24,"s":[12,-1.706,0],"to":[0,0,0],"ti":[0,0,0]},{"i":{"x":0.604,"y":0.579},"o":{"x":0.342,"y":0.381},"t":32,"s":[52.658,83.458,0],"to":[0,0,0],"ti":[0,0,0]},{"i":{"x":0.437,"y":1},"o":{"x":0.174,"y":0.441},"t":37,"s":[106.129,185.979,0],"to":[0,0,0],"ti":[0,0,0]},{"i":{"x":0.667,"y":0.667},"o":{"x":0.521,"y":0.521},"t":54,"s":[178,334.294,0],"to":[0,0,0],"ti":[0,0,0]},{"i":{"x":0.729,"y":0.636},"o":{"x":0.426,"y":0},"t":101,"s":[178,334.294,0],"to":[0,0,0],"ti":[0,0,0]},{"i":{"x":0.362,"y":0.548},"o":{"x":0.217,"y":0.236},"t":103,"s":[161.21,301.99,0],"to":[0,0,0],"ti":[0,0,0]},{"i":{"x":0.426,"y":1},"o":{"x":0.148,"y":0.444},"t":110,"s":[92.55,160.284,0],"to":[0,0,0],"ti":[0,0,0]},{"t":144,"s":[12,-1.706,0]}],"ix":2,"l":2},"a":{"a":0,"k":[10,-0.706,0],"ix":1,"l":2},"s":{"a":0,"k":[100,100,100],"ix":6,"l":2,"x":"var $bm_rt;\n$bm_rt = thisComp.layer('big cloud').content('big cloud').content('Group 1').transform.scale;"}},"ao":0,"shapes":[{"ty":"gr","it":[{"ind":0,"ty":"sh","ix":1,"ks":{"a":0,"k":{"i":[[0,37.531],[-12.215,18.859],[4.717,0],[11.548,-19.539],[12.638,-12.638],[-2.769,-11.217],[0,-21.139],[-30.765,0],[-10.125,10.447],[-17.463,0],[-11.043,7.263]],"o":[[0,-24.142],[-4.439,-0.936],[-24.34,0],[-13.404,-11.34],[-8.766,8.766],[-17.349,9.438],[0,30.765],[15.698,0],[12.273,10.563],[14.206,0],[-26.881,-22.122]],"v":[[45.912,-18.876],[65.225,-84.36],[51.469,-85.794],[-5.694,-53.148],[-51.819,-51.209],[-60.812,-18.876],[-89.936,30.089],[-34.231,85.794],[5.763,68.845],[51.469,85.794],[89.936,74.304]],"c":true},"ix":2},"nm":"Path 1","mn":"ADBE Vector Shape - Group","hd":false},{"ty":"fl","c":{"a":0,"k":[0.858823537827,0.29411765933,0.525490224361,1],"ix":4},"o":{"a":0,"k":100,"ix":5},"r":1,"bm":0,"nm":"Fill 1","mn":"ADBE Vector Graphic - Fill","hd":false},{"ty":"tr","p":{"a":0,"k":[198.531,164.294],"ix":2},"a":{"a":0,"k":[0,0],"ix":1},"s":{"a":0,"k":[100,100],"ix":3},"r":{"a":0,"k":0,"ix":6},"o":{"a":0,"k":100,"ix":7},"sk":{"a":0,"k":0,"ix":4},"sa":{"a":0,"k":0,"ix":5},"nm":"Transform"}],"nm":"Group 1","np":2,"cix":2,"bm":0,"ix":1,"mn":"ADBE Vector Group","hd":false},{"ty":"gr","it":[{"ind":0,"ty":"sh","ix":1,"ks":{"a":0,"k":{"i":[[17.349,9.438],[8.766,8.766],[13.404,-11.34],[24.34,0],[11.548,-19.539],[12.638,-12.638],[-2.769,-11.217],[0,-21.139],[-30.765,0],[-10.125,10.447],[-17.463,0],[-12.273,10.563],[-15.698,0],[0,30.765]],"o":[[2.769,-11.217],[-12.638,-12.638],[-11.548,-19.539],[-24.34,0],[-13.404,-11.34],[-8.766,8.766],[-17.349,9.438],[0,30.765],[15.698,0],[12.273,10.563],[17.463,0],[10.125,10.447],[30.765,0],[0,-21.139]],"v":[[112.281,-18.876],[103.288,-51.209],[57.163,-53.148],[0,-85.794],[-57.163,-53.148],[-103.288,-51.209],[-112.281,-18.876],[-141.405,30.089],[-85.699,85.794],[-45.706,68.845],[0,85.794],[45.706,68.845],[85.699,85.794],[141.405,30.089]],"c":true},"ix":2},"nm":"Path 1","mn":"ADBE Vector Shape - Group","hd":false},{"ty":"fl","c":{"a":0,"k":[0.992156863213,0.376470595598,0.313725501299,1],"ix":4},"o":{"a":0,"k":100,"ix":5},"r":1,"bm":0,"nm":"Fill 1","mn":"ADBE Vector Graphic - Fill","hd":false},{"ty":"tr","p":{"a":0,"k":[250,164.294],"ix":2},"a":{"a":0,"k":[0,0],"ix":1},"s":{"a":0,"k":[100,100],"ix":3},"r":{"a":0,"k":0,"ix":6},"o":{"a":0,"k":100,"ix":7},"sk":{"a":0,"k":0,"ix":4},"sa":{"a":0,"k":0,"ix":5},"nm":"Transform"}],"nm":"Group 2","np":2,"cix":2,"bm":0,"ix":2,"mn":"ADBE Vector Group","hd":false}],"ip":0,"op":180,"st":0,"ct":1,"bm":0},{"ddd":0,"ind":6,"ty":4,"nm":"lines","sr":1,"ks":{"o":{"a":0,"k":100,"ix":11},"r":{"a":0,"k":0,"ix":10},"p":{"a":0,"k":[250,304.314,0],"ix":2,"l":2},"a":{"a":0,"k":[250,304.314,0],"ix":1,"l":2},"s":{"a":0,"k":[100,100,100],"ix":6,"l":2}},"ao":0,"shapes":[{"ty":"gr","it":[{"ind":0,"ty":"sh","ix":1,"ks":{"a":1,"k":[{"t":24,"s":[{"i":[[0,0],[-3.992,-19.731]],"o":[[17.798,23.291],[0,0]],"v":[[-25.176,-76.48],[11.239,-1.959]],"c":false}],"h":1},{"i":{"x":0.833,"y":0.833},"o":{"x":0.333,"y":0},"t":126,"s":[{"i":[[0,0],[-6.18,-19.981]],"o":[[17.798,23.291],[0,0]],"v":[[-25.176,-76.48],[10.926,-1.834]],"c":false}]},{"t":159,"s":[{"i":[[0,0],[-3.992,-19.731]],"o":[[17.798,23.291],[0,0]],"v":[[-25.176,-76.48],[11.239,-1.959]],"c":false}],"h":1}],"ix":2},"nm":"Path 1","mn":"ADBE Vector Shape - Group","hd":false},{"ind":1,"ty":"sh","ix":2,"ks":{"a":1,"k":[{"t":24,"s":[{"i":[[0,0],[5.68,-21.231]],"o":[[-15.923,22.791],[0,0]],"v":[[120.295,-73.48],[92.442,-2.709]],"c":false}],"h":1},{"i":{"x":0.833,"y":0.833},"o":{"x":0.333,"y":0},"t":126,"s":[{"i":[[0,0],[5.68,-21.231]],"o":[[-15.923,22.791],[0,0]],"v":[[120.295,-73.48],[92.442,-2.709]],"c":false}]},{"t":159,"s":[{"i":[[0,0],[5.68,-21.231]],"o":[[-15.923,22.791],[0,0]],"v":[[120.295,-73.48],[92.442,-2.709]],"c":false}],"h":1}],"ix":2},"nm":"Path 2","mn":"ADBE Vector Shape - Group","hd":false},{"ty":"st","c":{"a":0,"k":[0.019607843831,0.164705887437,0.458823531866,1],"ix":3},"o":{"a":0,"k":100,"ix":4},"w":{"a":0,"k":16,"ix":5},"lc":1,"lj":2,"bm":0,"nm":"Stroke 1","mn":"ADBE Vector Graphic - Stroke","hd":false},{"ty":"tr","p":{"a":0,"k":[199.878,304.314],"ix":2},"a":{"a":0,"k":[0,0],"ix":1},"s":{"a":0,"k":[100,100],"ix":3},"r":{"a":0,"k":0,"ix":6},"o":{"a":1,"k":[{"i":{"x":[0.833],"y":[0.833]},"o":{"x":[0.167],"y":[0.167]},"t":22,"s":[100]},{"i":{"x":[0.833],"y":[0.833]},"o":{"x":[0.167],"y":[0.167]},"t":24,"s":[0]},{"i":{"x":[0.833],"y":[0.833]},"o":{"x":[0.167],"y":[0.167]},"t":156,"s":[0]},{"t":160,"s":[100]}],"ix":7},"sk":{"a":0,"k":0,"ix":4},"sa":{"a":0,"k":0,"ix":5},"nm":"Transform"}],"nm":"Group 1","np":3,"cix":2,"bm":0,"ix":1,"mn":"ADBE Vector Group","hd":false}],"ip":0,"op":180,"st":0,"ct":1,"bm":0},{"ddd":0,"ind":8,"ty":4,"nm":"ring FF","parent":2,"sr":1,"ks":{"o":{"a":1,"k":[{"i":{"x":[0.667],"y":[1]},"o":{"x":[0.333],"y":[0]},"t":14,"s":[100]},{"i":{"x":[0.667],"y":[1]},"o":{"x":[0.167],"y":[0]},"t":25,"s":[0]},{"i":{"x":[0.833],"y":[1]},"o":{"x":[0.167],"y":[0]},"t":159,"s":[0]},{"t":164,"s":[100]}],"ix":11},"r":{"a":0,"k":0,"ix":10},"p":{"a":1,"k":[{"i":{"x":0.667,"y":1},"o":{"x":0.333,"y":0},"t":45,"s":[60,104.718,0],"to":[0,0,0],"ti":[0,0,0]},{"i":{"x":0.667,"y":1},"o":{"x":0.333,"y":0},"t":134,"s":[60,167.718,0],"to":[0,0,0],"ti":[0,0,0]},{"t":170,"s":[60,104.718,0]}],"ix":2,"l":2},"a":{"a":0,"k":[0,0,0],"ix":1,"l":2},"s":{"a":0,"k":[100,100,100],"ix":6,"l":2}},"ao":0,"shapes":[{"ty":"gr","it":[{"ind":0,"ty":"sh","ix":1,"ks":{"a":0,"k":{"i":[[0,0]],"o":[[0,0]],"v":[[49.875,-19.749]],"c":false},"ix":2},"nm":"Path 1","mn":"ADBE Vector Shape - Group","hd":false},{"ty":"st","c":{"a":0,"k":[0.992156862745,0.560784313725,0.003921568627,1],"ix":3},"o":{"a":0,"k":100,"ix":4},"w":{"a":0,"k":16,"ix":5},"lc":1,"lj":1,"ml":4,"bm":0,"nm":"Stroke 1","mn":"ADBE Vector Graphic - Stroke","hd":false},{"ty":"fl","c":{"a":0,"k":[0.823528992896,0.862744978362,0.992156982422,1],"ix":4},"o":{"a":0,"k":100,"ix":5},"r":1,"bm":0,"nm":"Fill 1","mn":"ADBE Vector Graphic - Fill","hd":false},{"ty":"tr","p":{"a":0,"k":[0,0],"ix":2},"a":{"a":0,"k":[0,0],"ix":1},"s":{"a":0,"k":[100,100],"ix":3},"r":{"a":0,"k":0,"ix":6},"o":{"a":0,"k":100,"ix":7},"sk":{"a":0,"k":0,"ix":4},"sa":{"a":0,"k":0,"ix":5},"nm":"Transform"}],"nm":"Shape 1","np":3,"cix":2,"bm":0,"ix":1,"mn":"ADBE Vector Group","hd":false},{"ty":"gr","it":[{"ind":0,"ty":"sh","ix":1,"ks":{"a":1,"k":[{"i":{"x":0.833,"y":0.833},"o":{"x":0.167,"y":0.167},"t":157,"s":[{"i":[[-13.08,-2.128],[0,-8.116],[45.813,0],[0,13.067],[-20.638,4.304],[-0.714,0.139]],"o":[[21.833,4.262],[0,13.067],[-45.813,0],[0,-7.851],[0.697,-0.145],[13.441,-2.187]],"v":[[46.229,-19.834],[82.951,-0.17],[0,23.491],[-82.951,-0.17],[-48.908,-19.282],[-44.354,-19.732]],"c":false}]},{"t":170,"s":[{"i":[[-13.08,-2.128],[0,-8.116],[45.813,0],[0,13.067],[-20.017,4.32],[-1.088,0.212]],"o":[[21.833,4.262],[0,13.067],[-45.813,0],[0,-7.711],[1.05,-0.227],[13.441,-2.187]],"v":[[46.792,-19.709],[82.951,-0.17],[0,23.491],[-82.951,-0.17],[-50,-19.05],[-46.791,-19.709]],"c":false}]}],"ix":2},"nm":"Path 1","mn":"ADBE Vector Shape - Group","hd":false},{"ty":"st","c":{"a":0,"k":[0.20000000298,0.800000011921,0.800000011921,1],"ix":3,"x":"var $bm_rt;\n$bm_rt = thisComp.layer('Main Stroke width - Color Ctrl').effect('Highlight')('Color');"},"o":{"a":0,"k":100,"ix":4},"w":{"a":0,"k":16,"ix":5,"x":"var $bm_rt;\n$bm_rt = thisComp.layer('Main Stroke width - Color Ctrl').effect('Stroke width')('Slider');"},"lc":1,"lj":2,"bm":0,"nm":"Stroke 1","mn":"ADBE Vector Graphic - Stroke","hd":false},{"ty":"tr","p":{"a":0,"k":[0,0],"ix":2},"a":{"a":0,"k":[0,0],"ix":1},"s":{"a":0,"k":[100,100],"ix":3},"r":{"a":0,"k":0,"ix":6},"o":{"a":0,"k":100,"ix":7},"sk":{"a":0,"k":0,"ix":4},"sa":{"a":0,"k":0,"ix":5},"nm":"Transform"}],"nm":"ring front","np":2,"cix":2,"bm":0,"ix":2,"mn":"ADBE Vector Group","hd":false}],"ip":0,"op":180,"st":0,"ct":1,"bm":0},{"ddd":0,"ind":9,"ty":0,"nm":"middle mask","td":1,"refId":"comp_1","sr":1,"ks":{"o":{"a":0,"k":100,"ix":11},"r":{"a":0,"k":0,"ix":10},"p":{"a":0,"k":[250,250,0],"ix":2,"l":2},"a":{"a":0,"k":[250,250,0],"ix":1,"l":2},"s":{"a":0,"k":[100,100,100],"ix":6,"l":2}},"ao":0,"w":500,"h":500,"ip":0,"op":180,"st":0,"bm":0},{"ddd":0,"ind":10,"ty":4,"nm":"middle cloud","tt":2,"tp":9,"sr":1,"ks":{"o":{"a":0,"k":100,"ix":11},"r":{"a":0,"k":0,"ix":10},"p":{"a":0,"k":[250,328.03,0],"ix":2,"l":2},"a":{"a":0,"k":[0,0,0],"ix":1,"l":2},"s":{"a":0,"k":[100,100,100],"ix":6,"l":2}},"ao":0,"shapes":[{"ty":"gr","it":[{"ind":0,"ty":"sh","ix":1,"ks":{"a":1,"k":[{"i":{"x":0.833,"y":0.833},"o":{"x":0.07,"y":0},"t":23,"s":[{"i":[[0,0],[0,-29.935],[0,0],[-17.087,0.551],[-4.483,15.929],[-2.445,20.394],[-12.548,29.416]],"o":[[21.423,23.166],[0,0],[4.747,16.796],[16.227,-0.524],[0,-20.226],[7.055,-38.231],[0,0]],"v":[[-80.423,-105.571],[-35.57,-3.299],[-36.808,57.379],[0.601,85.052],[35.57,57.379],[36.82,-3.799],[74.173,-115.571]],"c":false}]},{"i":{"x":0.4,"y":1},"o":{"x":0.167,"y":0.167},"t":30,"s":[{"i":[[0,0],[0.57,-19.318],[0,0],[-17.087,0.551],[-4.483,15.929],[-1.19,12.086],[-9.272,25.095]],"o":[[15.916,19.32],[0,0],[4.747,16.796],[16.227,-0.524],[0.258,-13.269],[5.271,-25.745],[0,0]],"v":[[-80.892,-85.229],[-35.639,17.685],[-36.808,57.379],[0.601,85.052],[35.57,57.379],[34.853,18.134],[70.593,-77.687]],"c":false}]},{"i":{"x":0.13,"y":1},"o":{"x":0.167,"y":0},"t":54,"s":[{"i":[[0,0],[1.5,-1.981],[0,0],[-17.087,0.551],[-4.483,15.929],[0.859,-1.481],[-3.923,18.041]],"o":[[6.923,13.041],[0,0],[4.747,16.796],[16.227,-0.524],[0.68,-1.909],[2.359,-5.356],[0,0]],"v":[[-34.923,37.179],[-35.75,51.951],[-36.808,57.379],[0.601,85.052],[35.57,57.379],[31.641,53.951],[34.798,42.429]],"c":false}]},{"i":{"x":0.13,"y":1},"o":{"x":0.07,"y":0},"t":101,"s":[{"i":[[0,0],[1.5,-1.981],[0,0],[-17.087,0.551],[-4.483,15.929],[0.859,-1.481],[-3.923,18.041]],"o":[[6.923,13.041],[0,0],[4.747,16.796],[16.227,-0.524],[0.68,-1.909],[2.359,-5.356],[0,0]],"v":[[-34.923,37.179],[-35.75,51.951],[-36.808,57.379],[0.601,85.052],[35.57,57.379],[31.641,53.951],[34.798,42.429]],"c":false}]},{"t":144,"s":[{"i":[[0,0],[0,-29.935],[0,0],[-17.087,0.551],[-4.483,15.929],[-2.445,20.394],[-12.548,29.416]],"o":[[21.423,23.166],[0,0],[4.747,16.796],[16.227,-0.524],[0,-20.226],[7.055,-38.231],[0,0]],"v":[[-80.423,-105.571],[-35.57,-3.299],[-36.808,57.379],[0.601,85.052],[35.57,57.379],[36.82,-3.799],[74.173,-115.571]],"c":false}]}],"ix":2},"nm":"Path 1","mn":"ADBE Vector Shape - Group","hd":false},{"ty":"st","c":{"a":0,"k":[0,0,0,1],"ix":3,"x":"var $bm_rt;\n$bm_rt = thisComp.layer('Main Stroke width - Color Ctrl').effect('Base Color')('Color');"},"o":{"a":0,"k":100,"ix":4},"w":{"a":0,"k":16,"ix":5,"x":"var $bm_rt;\n$bm_rt = thisComp.layer('Main Stroke width - Color Ctrl').effect('Stroke width')('Slider');"},"lc":1,"lj":2,"bm":0,"nm":"Stroke 1","mn":"ADBE Vector Graphic - Stroke","hd":false},{"ty":"tr","p":{"a":0,"k":[0,0],"ix":2},"a":{"a":0,"k":[0,0],"ix":1},"s":{"a":0,"k":[100,100],"ix":3},"r":{"a":0,"k":0,"ix":6},"o":{"a":0,"k":100,"ix":7},"sk":{"a":0,"k":0,"ix":4},"sa":{"a":0,"k":0,"ix":5},"nm":"Transform"}],"nm":"middle cloud","np":2,"cix":2,"bm":0,"ix":1,"mn":"ADBE Vector Group","hd":false},{"ty":"fl","c":{"a":0,"k":[0.992156862745,0.796078431373,0.313725490196,1],"ix":4},"o":{"a":0,"k":100,"ix":5},"r":1,"bm":0,"nm":"Fill 1","mn":"ADBE Vector Graphic - Fill","hd":false}],"ip":0,"op":180,"st":0,"ct":1,"bm":0},{"ddd":0,"ind":11,"ty":4,"nm":"small cloud 3","td":1,"sr":1,"ks":{"o":{"a":0,"k":100,"ix":11},"r":{"a":0,"k":0,"ix":10},"p":{"a":0,"k":[250,384.768,0],"ix":2,"l":2},"a":{"a":0,"k":[0,0,0],"ix":1,"l":2},"s":{"a":0,"k":[100,100,100],"ix":6,"l":2}},"ao":0,"shapes":[{"ty":"gr","it":[{"ty":"gr","it":[{"ind":0,"ty":"sh","ix":1,"ks":{"a":0,"k":{"i":[[0,0],[-9.001,-9.001],[12.648,-12.648],[0,0],[-12.648,12.648],[-11.296,-3.809]],"o":[[11.296,-3.809],[12.648,12.648],[0,0],[-12.648,-12.648],[9.001,-9.001],[0,0]],"v":[[41.877,-16.85],[73.465,-9.07],[73.465,36.732],[-73.465,36.732],[-73.465,-9.07],[-37.877,-19.288]],"c":false},"ix":2},"nm":"Path 2","mn":"ADBE Vector Shape - Group","hd":false},{"ty":"fl","c":{"a":0,"k":[1,0,0,1],"ix":4},"o":{"a":0,"k":100,"ix":5},"r":1,"bm":0,"nm":"Fill 1","mn":"ADBE Vector Graphic - Fill","hd":false},{"ty":"tr","p":{"a":0,"k":[0,0],"ix":2},"a":{"a":0,"k":[0,0],"ix":1},"s":{"a":1,"k":[{"i":{"x":[0.4,0.4],"y":[1,1]},"o":{"x":[0.333,0.333],"y":[0,0]},"t":23,"s":[100,100]},{"i":{"x":[0.4,0.4],"y":[1,1]},"o":{"x":[0.167,0.167],"y":[0,0]},"t":54,"s":[75,75]},{"i":{"x":[0.667,0.667],"y":[1,1]},"o":{"x":[0.167,0.167],"y":[0,0]},"t":101,"s":[75,75]},{"t":135,"s":[100,100]}],"ix":3},"r":{"a":0,"k":0,"ix":6},"o":{"a":0,"k":100,"ix":7},"sk":{"a":0,"k":0,"ix":4},"sa":{"a":0,"k":0,"ix":5},"nm":"Transform"}],"nm":"Group 2","np":3,"cix":2,"bm":0,"ix":1,"mn":"ADBE Vector Group","hd":false},{"ty":"gr","it":[{"ind":0,"ty":"sh","ix":1,"ks":{"a":0,"k":{"i":[[0,0],[25.238,0],[0.695,-3.95]],"o":[[-2.445,-18.7],[-25.238,0],[0,0]],"v":[[43.445,-16.568],[0,-36.732],[-37.195,-17.318]],"c":false},"ix":2},"nm":"Path 1","mn":"ADBE Vector Shape - Group","hd":false},{"ty":"fl","c":{"a":0,"k":[1,0,0,1],"ix":4},"o":{"a":0,"k":100,"ix":5},"r":1,"bm":0,"nm":"Fill 1","mn":"ADBE Vector Graphic - Fill","hd":false},{"ty":"tr","p":{"a":0,"k":[0,0],"ix":2},"a":{"a":0,"k":[0,0],"ix":1},"s":{"a":1,"k":[{"i":{"x":[0.4,0.4],"y":[1,1]},"o":{"x":[0.333,0.333],"y":[0,0]},"t":23,"s":[100,100]},{"i":{"x":[0.4,0.4],"y":[1,1]},"o":{"x":[0.167,0.167],"y":[0,0]},"t":54,"s":[75,75]},{"i":{"x":[0.667,0.667],"y":[1,1]},"o":{"x":[0.167,0.167],"y":[0,0]},"t":101,"s":[75,75]},{"t":135,"s":[100,100]}],"ix":3},"r":{"a":0,"k":0,"ix":6},"o":{"a":0,"k":100,"ix":7},"sk":{"a":0,"k":0,"ix":4},"sa":{"a":0,"k":0,"ix":5},"nm":"Transform"}],"nm":"Group 1","np":3,"cix":2,"bm":0,"ix":2,"mn":"ADBE Vector Group","hd":false},{"ty":"tr","p":{"a":0,"k":[0,0],"ix":2},"a":{"a":0,"k":[0,0],"ix":1},"s":{"a":0,"k":[100,100],"ix":3},"r":{"a":0,"k":0,"ix":6},"o":{"a":0,"k":100,"ix":7},"sk":{"a":0,"k":0,"ix":4},"sa":{"a":0,"k":0,"ix":5},"nm":"Transform"}],"nm":"small cloud","np":3,"cix":2,"bm":0,"ix":1,"mn":"ADBE Vector Group","hd":false}],"ip":0,"op":180,"st":0,"ct":1,"bm":0},{"ddd":0,"ind":12,"ty":4,"nm":"explosion","tt":2,"tp":11,"sr":1,"ks":{"o":{"a":0,"k":100,"ix":11},"r":{"a":0,"k":0,"ix":10},"p":{"a":1,"k":[{"i":{"x":0.4,"y":1},"o":{"x":0.07,"y":0},"t":54,"s":[250,371.62,0],"to":[0,0,0],"ti":[0,0,0]},{"i":{"x":0.4,"y":1},"o":{"x":0.07,"y":0},"t":116,"s":[250,396.62,0],"to":[0,0,0],"ti":[0,0,0]},{"t":169,"s":[250,371.62,0]}],"ix":2,"l":2},"a":{"a":0,"k":[0,0,0],"ix":1,"l":2},"s":{"a":0,"k":[100,100,100],"ix":6,"l":2}},"ao":0,"shapes":[{"ty":"gr","it":[{"ty":"rc","d":1,"s":{"a":0,"k":[443,213],"ix":2},"p":{"a":0,"k":[0,0],"ix":3},"r":{"a":0,"k":0,"ix":4},"nm":"Rectangle Path 1","mn":"ADBE Vector Shape - Rect","hd":false},{"ty":"fl","c":{"a":0,"k":[1,0,0,1],"ix":4},"o":{"a":0,"k":100,"ix":5},"r":1,"bm":0,"nm":"Fill 1","mn":"ADBE Vector Graphic - Fill","hd":false},{"ty":"tr","p":{"a":0,"k":[7,8.67],"ix":2},"a":{"a":0,"k":[0,0],"ix":1},"s":{"a":0,"k":[100,100],"ix":3},"r":{"a":0,"k":0,"ix":6},"o":{"a":0,"k":0,"ix":7},"sk":{"a":0,"k":0,"ix":4},"sa":{"a":0,"k":0,"ix":5},"nm":"Transform"}],"nm":"Rectangle 1","np":3,"cix":2,"bm":0,"ix":1,"mn":"ADBE Vector Group","hd":false},{"ty":"gr","it":[{"ty":"gr","it":[{"ind":0,"ty":"sh","ix":1,"ks":{"a":0,"k":{"i":[[0,0],[0,-7.895],[-6.375,-3.689]],"o":[[-6.375,3.689],[0,7.895],[0,0]],"v":[[-132.3,-0.808],[-142.966,17.663],[-132.3,36.134]],"c":false},"ix":2},"nm":"Path 1","mn":"ADBE Vector Shape - Group","hd":false},{"ind":1,"ty":"sh","ix":2,"ks":{"a":0,"k":{"i":[[0,0],[1.02,-10.523]],"o":[[-10.523,-1.02],[0,0]],"v":[[-85.662,-36.044],[-106.562,-18.837]],"c":false},"ix":2},"nm":"Path 2","mn":"ADBE Vector Shape - Group","hd":false},{"ind":2,"ty":"sh","ix":3,"ks":{"a":0,"k":{"i":[[0,0],[0,7.895],[6.375,3.689]],"o":[[6.375,-3.689],[0,-7.895],[0,0]],"v":[[132.3,36.134],[142.966,17.663],[132.3,-0.808]],"c":false},"ix":2},"nm":"Path 3","mn":"ADBE Vector Shape - Group","hd":false},{"ind":3,"ty":"sh","ix":4,"ks":{"a":0,"k":{"i":[[0,0],[-1.02,-10.523]],"o":[[10.523,-1.02],[0,0]],"v":[[85.662,-36.044],[106.562,-18.837]],"c":false},"ix":2},"nm":"Path 4","mn":"ADBE Vector Shape - Group","hd":false},{"ty":"tr","p":{"a":0,"k":[0,0],"ix":2},"a":{"a":0,"k":[0,0],"ix":1},"s":{"a":1,"k":[{"i":{"x":[0.833,0.833],"y":[1,1]},"o":{"x":[0.167,0.167],"y":[0,0]},"t":115,"s":[55,55]},{"t":169,"s":[100,100]}],"ix":3},"r":{"a":0,"k":0,"ix":6},"o":{"a":0,"k":100,"ix":7},"sk":{"a":0,"k":0,"ix":4},"sa":{"a":0,"k":0,"ix":5},"nm":"Transform"}],"nm":"Group 1","np":4,"cix":2,"bm":0,"ix":1,"mn":"ADBE Vector Group","hd":false},{"ty":"st","c":{"a":0,"k":[0.20000000298,0.800000011921,0.800000011921,1],"ix":3,"x":"var $bm_rt;\n$bm_rt = thisComp.layer('Main Stroke width - Color Ctrl').effect('Highlight')('Color');"},"o":{"a":0,"k":100,"ix":4},"w":{"a":0,"k":16,"ix":5,"x":"var $bm_rt;\n$bm_rt = thisComp.layer('Main Stroke width - Color Ctrl').effect('Stroke width')('Slider');"},"lc":2,"lj":2,"bm":0,"nm":"Stroke 1","mn":"ADBE Vector Graphic - Stroke","hd":false},{"ty":"tr","p":{"a":0,"k":[0,0],"ix":2},"a":{"a":0,"k":[0,0],"ix":1},"s":{"a":0,"k":[100,100],"ix":3},"r":{"a":0,"k":0,"ix":6},"o":{"a":1,"k":[{"i":{"x":[0.833],"y":[1]},"o":{"x":[0.167],"y":[0]},"t":115,"s":[0]},{"t":122,"s":[100]}],"ix":7},"sk":{"a":0,"k":0,"ix":4},"sa":{"a":0,"k":0,"ix":5},"nm":"Transform"}],"nm":"explosion 2","np":2,"cix":2,"bm":0,"ix":2,"mn":"ADBE Vector Group","hd":false},{"ty":"gr","it":[{"ty":"gr","it":[{"ind":0,"ty":"sh","ix":1,"ks":{"a":0,"k":{"i":[[0,0],[0,-7.895],[-6.375,-3.689]],"o":[[-6.375,3.689],[0,7.895],[0,0]],"v":[[-132.3,-0.808],[-142.966,17.663],[-132.3,36.134]],"c":false},"ix":2},"nm":"Path 1","mn":"ADBE Vector Shape - Group","hd":false},{"ind":1,"ty":"sh","ix":2,"ks":{"a":0,"k":{"i":[[0,0],[1.02,-10.523]],"o":[[-10.523,-1.02],[0,0]],"v":[[-85.662,-36.044],[-106.562,-18.837]],"c":false},"ix":2},"nm":"Path 2","mn":"ADBE Vector Shape - Group","hd":false},{"ind":2,"ty":"sh","ix":3,"ks":{"a":0,"k":{"i":[[0,0],[0,7.895],[6.375,3.689]],"o":[[6.375,-3.689],[0,-7.895],[0,0]],"v":[[132.3,36.134],[142.966,17.663],[132.3,-0.808]],"c":false},"ix":2},"nm":"Path 3","mn":"ADBE Vector Shape - Group","hd":false},{"ind":3,"ty":"sh","ix":4,"ks":{"a":0,"k":{"i":[[0,0],[-1.02,-10.523]],"o":[[10.523,-1.02],[0,0]],"v":[[85.662,-36.044],[106.562,-18.837]],"c":false},"ix":2},"nm":"Path 4","mn":"ADBE Vector Shape - Group","hd":false},{"ty":"tr","p":{"a":0,"k":[0,0],"ix":2},"a":{"a":0,"k":[0,0],"ix":1},"s":{"a":1,"k":[{"i":{"x":[0.667,0.667],"y":[1,1]},"o":{"x":[0.333,0.333],"y":[0,0]},"t":14,"s":[100,100]},{"t":49,"s":[115,115]}],"ix":3},"r":{"a":0,"k":0,"ix":6},"o":{"a":0,"k":100,"ix":7},"sk":{"a":0,"k":0,"ix":4},"sa":{"a":0,"k":0,"ix":5},"nm":"Transform"}],"nm":"Group 1","np":4,"cix":2,"bm":0,"ix":1,"mn":"ADBE Vector Group","hd":false},{"ty":"st","c":{"a":0,"k":[0.20000000298,0.800000011921,0.800000011921,1],"ix":3,"x":"var $bm_rt;\n$bm_rt = thisComp.layer('Main Stroke width - Color Ctrl').effect('Highlight')('Color');"},"o":{"a":0,"k":100,"ix":4},"w":{"a":0,"k":16,"ix":5,"x":"var $bm_rt;\n$bm_rt = thisComp.layer('Main Stroke width - Color Ctrl').effect('Stroke width')('Slider');"},"lc":2,"lj":2,"bm":0,"nm":"Stroke 1","mn":"ADBE Vector Graphic - Stroke","hd":false},{"ty":"tr","p":{"a":0,"k":[0,0],"ix":2},"a":{"a":0,"k":[0,0],"ix":1},"s":{"a":0,"k":[100,100],"ix":3},"r":{"a":0,"k":0,"ix":6},"o":{"a":1,"k":[{"i":{"x":[0.667],"y":[1]},"o":{"x":[0.333],"y":[0]},"t":41,"s":[100]},{"t":49,"s":[0]}],"ix":7},"sk":{"a":0,"k":0,"ix":4},"sa":{"a":0,"k":0,"ix":5},"nm":"Transform"}],"nm":"explosion","np":2,"cix":2,"bm":0,"ix":3,"mn":"ADBE Vector Group","hd":false}],"ip":0,"op":180,"st":0,"ct":1,"bm":0}]},{"id":"comp_1","nm":"middle mask","fr":60,"layers":[{"ddd":0,"ind":1,"ty":4,"nm":"big cloud 2","sr":1,"ks":{"o":{"a":0,"k":100,"ix":11},"r":{"a":0,"k":0,"ix":10},"p":{"a":0,"k":[250,164.294,0],"ix":2,"l":2},"a":{"a":0,"k":[0,0,0],"ix":1,"l":2},"s":{"a":0,"k":[100,100,100],"ix":6,"l":2}},"ao":0,"shapes":[{"ty":"gr","it":[{"ty":"gr","it":[{"ind":0,"ty":"sh","ix":1,"ks":{"a":0,"k":{"i":[[0,0],[13.323,13.323],[13.404,-11.325]],"o":[[13.323,-13.323],[-12.633,-12.633],[0,0]],"v":[[103.288,-2.962],[103.288,-51.209],[57.174,-53.171]],"c":false},"ix":2},"nm":"Path 1","mn":"ADBE Vector Shape - Group","hd":false},{"ind":1,"ty":"sh","ix":2,"ks":{"a":0,"k":{"i":[[0,0],[12.637,-12.637],[-13.323,-13.323]],"o":[[-13.404,-11.337],[-13.323,13.323],[0,0]],"v":[[-57.161,-53.16],[-103.288,-51.209],[-103.288,-2.962]],"c":false},"ix":2},"nm":"Path 2","mn":"ADBE Vector Shape - Group","hd":false},{"ind":2,"ty":"sh","ix":3,"ks":{"a":0,"k":{"i":[[0,0],[32.812,0],[5.345,-31.288]],"o":[[-5.345,-31.288],[-32.812,0],[0,0]],"v":[[65.402,-30.69],[0,-85.794],[-65.402,-30.69]],"c":false},"ix":2},"nm":"Path 3","mn":"ADBE Vector Shape - Group","hd":false},{"ind":3,"ty":"sh","ix":4,"ks":{"a":0,"k":{"i":[[0,0],[-29.3,0],[-10.477,25.524]],"o":[[10.477,25.524],[29.3,0],[0,0]],"v":[[-64.868,42.289],[0,85.794],[64.868,42.289]],"c":false},"ix":2},"nm":"Path 4","mn":"ADBE Vector Shape - Group","hd":false},{"ind":4,"ty":"sh","ix":5,"ks":{"a":0,"k":{"i":[[0,0],[0,-21.139],[-30.765,0],[-10.125,10.447]],"o":[[-17.349,9.438],[0,30.765],[15.698,0],[0,0]],"v":[[-112.281,-18.876],[-141.405,30.089],[-85.699,85.794],[-45.706,68.845]],"c":false},"ix":2},"nm":"Path 5","mn":"ADBE Vector Shape - Group","hd":false},{"ind":5,"ty":"sh","ix":6,"ks":{"a":0,"k":{"i":[[0,0],[0,-21.139],[30.765,0],[10.125,10.447]],"o":[[17.349,9.438],[0,30.765],[-15.698,0],[0,0]],"v":[[112.281,-18.876],[141.405,30.089],[85.699,85.794],[45.706,68.845]],"c":false},"ix":2},"nm":"Path 6","mn":"ADBE Vector Shape - Group","hd":false},{"ty":"tr","p":{"a":0,"k":[0,0],"ix":2},"a":{"a":0,"k":[0,0],"ix":1},"s":{"a":1,"k":[{"i":{"x":[0.4,0.4],"y":[1,1]},"o":{"x":[0.333,0.333],"y":[0,0]},"t":24,"s":[100,100]},{"i":{"x":[0.13,0.13],"y":[1,1]},"o":{"x":[0.167,0.167],"y":[0,0]},"t":54,"s":[30,30]},{"i":{"x":[0.13,0.13],"y":[1,1]},"o":{"x":[0.07,0.07],"y":[0,0]},"t":101,"s":[30,30]},{"t":144,"s":[100,100]}],"ix":3},"r":{"a":0,"k":0,"ix":6},"o":{"a":0,"k":100,"ix":7},"sk":{"a":0,"k":0,"ix":4},"sa":{"a":0,"k":0,"ix":5},"nm":"Transform"}],"nm":"Group 1","np":6,"cix":2,"bm":0,"ix":1,"mn":"ADBE Vector Group","hd":false},{"ty":"tr","p":{"a":1,"k":[{"i":{"x":0.4,"y":1},"o":{"x":0.333,"y":0},"t":24,"s":[0,0],"to":[0,0],"ti":[0,0]},{"i":{"x":0.13,"y":0.13},"o":{"x":0.167,"y":0.167},"t":54,"s":[0,221],"to":[0,0],"ti":[0,0]},{"i":{"x":0.13,"y":1},"o":{"x":0.07,"y":0},"t":101,"s":[0,221],"to":[0,0],"ti":[0,0]},{"t":144,"s":[0,0]}],"ix":2},"a":{"a":0,"k":[0,0],"ix":1},"s":{"a":0,"k":[100,100],"ix":3},"r":{"a":0,"k":0,"ix":6},"o":{"a":0,"k":100,"ix":7},"sk":{"a":0,"k":0,"ix":4},"sa":{"a":0,"k":0,"ix":5},"nm":"Transform"}],"nm":"big cloud","np":2,"cix":2,"bm":0,"ix":1,"mn":"ADBE Vector Group","hd":false},{"ty":"gr","it":[{"ind":0,"ty":"sh","ix":1,"ks":{"a":0,"k":{"i":[[11,2.875],[0,0],[9.875,-1.625],[10.375,-17.625],[-7.625,-3.5],[0,0],[-11.875,-4.75],[0,0],[-8.75,-2.625],[2.5,21.375],[9.375,4.5]],"o":[[-11,-2.875],[0,0],[-9.875,1.625],[-10.375,17.625],[7.625,3.5],[0,0],[11.875,4.75],[0,0],[8.75,2.625],[-2.5,-21.375],[-9.375,-4.5]],"v":[[0.375,44.875],[-26.75,57.625],[-42.375,55.125],[-63.875,85.75],[-46,121.75],[-24.25,113.5],[-8.125,123.625],[18,113.125],[37.875,122.375],[61.75,92.75],[30.75,57.375]],"c":true},"ix":2},"nm":"Path 1","mn":"ADBE Vector Shape - Group","hd":false},{"ty":"fl","c":{"a":0,"k":[0.992156862745,0.376470588235,0.313725490196,1],"ix":4},"o":{"a":0,"k":100,"ix":5},"r":1,"bm":0,"nm":"Fill 1","mn":"ADBE Vector Graphic - Fill","hd":false},{"ty":"tr","p":{"a":1,"k":[{"i":{"x":0.528,"y":0.176},"o":{"x":0.174,"y":0},"t":24,"s":[1,-2.25],"to":[0,0],"ti":[0,0]},{"i":{"x":0.639,"y":0.713},"o":{"x":0.303,"y":0.227},"t":30,"s":[1,30.86],"to":[0,0],"ti":[0,0]},{"i":{"x":0.643,"y":0.74},"o":{"x":0.304,"y":0.269},"t":34,"s":[1,82.391],"to":[0,0],"ti":[0,0]},{"i":{"x":0.666,"y":1},"o":{"x":0.322,"y":0.753},"t":42,"s":[1,174.999],"to":[0,0],"ti":[0,0]},{"i":{"x":0.667,"y":0.667},"o":{"x":0.07,"y":0.07},"t":55,"s":[1,221.75],"to":[0,0],"ti":[0,0]},{"i":{"x":0.667,"y":0.773},"o":{"x":0.333,"y":0},"t":101,"s":[1,221.75],"to":[0,0],"ti":[0,0]},{"i":{"x":0.667,"y":0.762},"o":{"x":0.333,"y":0.309},"t":107,"s":[1,141.523],"to":[0,0],"ti":[0,0]},{"i":{"x":0.667,"y":0.499},"o":{"x":0.333,"y":0.454},"t":114,"s":[1,72.656],"to":[0,0],"ti":[0,0]},{"i":{"x":0.667,"y":1},"o":{"x":0.216,"y":1},"t":121,"s":[1,36.451],"to":[0,0],"ti":[0,0]},{"t":144,"s":[1,-2.25]}],"ix":2},"a":{"a":0,"k":[0,81],"ix":1},"s":{"a":1,"k":[{"i":{"x":[0.26,0.26],"y":[0.364,0.364]},"o":{"x":[0.136,0.136],"y":[0,0]},"t":24,"s":[210,210]},{"i":{"x":[0.592,0.592],"y":[0.737,0.737]},"o":{"x":[0.264,0.264],"y":[0.2,0.2]},"t":34,"s":[152.797,152.797]},{"i":{"x":[0.599,0.599],"y":[1,1]},"o":{"x":[0.271,0.271],"y":[0.99,0.99]},"t":42,"s":[100.867,100.867]},{"i":{"x":[0.667,0.667],"y":[1,1]},"o":{"x":[0.07,0.07],"y":[0,0]},"t":55,"s":[86,86]},{"i":{"x":[0.667,0.667],"y":[0.705,0.705]},"o":{"x":[0.333,0.333],"y":[0,0]},"t":101,"s":[86,86]},{"i":{"x":[0.667,0.667],"y":[1,1]},"o":{"x":[0.333,0.333],"y":[1.232,1.232]},"t":121,"s":[174.597,174.597]},{"t":144,"s":[199,199]}],"ix":3},"r":{"a":0,"k":0,"ix":6},"o":{"a":0,"k":100,"ix":7},"sk":{"a":0,"k":0,"ix":4},"sa":{"a":0,"k":0,"ix":5},"nm":"Transform"}],"nm":"Shape 1","np":3,"cix":2,"bm":0,"ix":2,"mn":"ADBE Vector Group","hd":false},{"ty":"fl","c":{"a":0,"k":[1,0,0,1],"ix":4},"o":{"a":0,"k":100,"ix":5},"r":1,"bm":0,"nm":"Fill 1","mn":"ADBE Vector Graphic - Fill","hd":false}],"ip":0,"op":180,"st":0,"ct":1,"bm":0},{"ddd":0,"ind":2,"ty":4,"nm":"small cloud 2","sr":1,"ks":{"o":{"a":0,"k":100,"ix":11},"r":{"a":0,"k":0,"ix":10},"p":{"a":0,"k":[250,384.768,0],"ix":2,"l":2},"a":{"a":0,"k":[0,0,0],"ix":1,"l":2},"s":{"a":0,"k":[100,100,100],"ix":6,"l":2}},"ao":0,"shapes":[{"ty":"gr","it":[{"ty":"gr","it":[{"ind":0,"ty":"sh","ix":1,"ks":{"a":0,"k":{"i":[[0,0],[-9.001,-9.001],[12.648,-12.648],[0,0],[-12.648,12.648],[-11.296,-3.809]],"o":[[11.296,-3.809],[12.648,12.648],[0,0],[-12.648,-12.648],[9.001,-9.001],[0,0]],"v":[[41.877,-16.85],[73.465,-9.07],[73.465,36.732],[-73.465,36.732],[-73.465,-9.07],[-37.877,-19.288]],"c":false},"ix":2},"nm":"Path 2","mn":"ADBE Vector Shape - Group","hd":false},{"ty":"fl","c":{"a":0,"k":[1,0,0,1],"ix":4},"o":{"a":0,"k":100,"ix":5},"r":1,"bm":0,"nm":"Fill 1","mn":"ADBE Vector Graphic - Fill","hd":false},{"ty":"tr","p":{"a":0,"k":[0,0],"ix":2},"a":{"a":0,"k":[0,0],"ix":1},"s":{"a":1,"k":[{"i":{"x":[0.4,0.4],"y":[1,1]},"o":{"x":[0.333,0.333],"y":[0,0]},"t":23,"s":[100,100]},{"i":{"x":[0.4,0.4],"y":[1,1]},"o":{"x":[0.167,0.167],"y":[0,0]},"t":54,"s":[75,75]},{"i":{"x":[0.667,0.667],"y":[1,1]},"o":{"x":[0.167,0.167],"y":[0,0]},"t":101,"s":[75,75]},{"t":135,"s":[100,100]}],"ix":3},"r":{"a":0,"k":0,"ix":6},"o":{"a":0,"k":100,"ix":7},"sk":{"a":0,"k":0,"ix":4},"sa":{"a":0,"k":0,"ix":5},"nm":"Transform"}],"nm":"Group 2","np":3,"cix":2,"bm":0,"ix":1,"mn":"ADBE Vector Group","hd":false},{"ty":"gr","it":[{"ind":0,"ty":"sh","ix":1,"ks":{"a":0,"k":{"i":[[0,0],[25.238,0],[0.695,-3.95]],"o":[[-2.445,-18.7],[-25.238,0],[0,0]],"v":[[43.445,-16.568],[0,-36.732],[-37.195,-17.318]],"c":false},"ix":2},"nm":"Path 1","mn":"ADBE Vector Shape - Group","hd":false},{"ty":"fl","c":{"a":0,"k":[1,0,0,1],"ix":4},"o":{"a":0,"k":100,"ix":5},"r":1,"bm":0,"nm":"Fill 1","mn":"ADBE Vector Graphic - Fill","hd":false},{"ty":"tr","p":{"a":0,"k":[0,0],"ix":2},"a":{"a":0,"k":[0,0],"ix":1},"s":{"a":1,"k":[{"i":{"x":[0.4,0.4],"y":[1,1]},"o":{"x":[0.333,0.333],"y":[0,0]},"t":23,"s":[100,100]},{"i":{"x":[0.4,0.4],"y":[1,1]},"o":{"x":[0.167,0.167],"y":[0,0]},"t":54,"s":[75,75]},{"i":{"x":[0.667,0.667],"y":[1,1]},"o":{"x":[0.167,0.167],"y":[0,0]},"t":101,"s":[75,75]},{"t":135,"s":[100,100]}],"ix":3},"r":{"a":0,"k":0,"ix":6},"o":{"a":0,"k":100,"ix":7},"sk":{"a":0,"k":0,"ix":4},"sa":{"a":0,"k":0,"ix":5},"nm":"Transform"}],"nm":"Group 1","np":3,"cix":2,"bm":0,"ix":2,"mn":"ADBE Vector Group","hd":false},{"ty":"tr","p":{"a":0,"k":[0,0],"ix":2},"a":{"a":0,"k":[0,0],"ix":1},"s":{"a":0,"k":[100,100],"ix":3},"r":{"a":0,"k":0,"ix":6},"o":{"a":0,"k":100,"ix":7},"sk":{"a":0,"k":0,"ix":4},"sa":{"a":0,"k":0,"ix":5},"nm":"Transform"}],"nm":"small cloud","np":3,"cix":2,"bm":0,"ix":1,"mn":"ADBE Vector Group","hd":false}],"ip":0,"op":180,"st":0,"ct":1,"bm":0}]}],"layers":[{"ddd":0,"ind":1,"ty":1,"nm":"Main Stroke width - Color Ctrl","sr":1,"ks":{"o":{"a":0,"k":0,"ix":11},"r":{"a":0,"k":0,"ix":10},"p":{"a":0,"k":[250,250,0],"ix":2,"l":2},"a":{"a":0,"k":[50,50,0],"ix":1,"l":2},"s":{"a":0,"k":[100,100,100],"ix":6,"l":2}},"ao":0,"ef":[{"ty":5,"nm":"Stroke width","np":3,"mn":"ADBE Slider Control","ix":1,"en":1,"ef":[{"ty":0,"nm":"Slider","mn":"ADBE Slider Control-0001","ix":1,"v":{"a":0,"k":16,"ix":1}}]},{"ty":5,"nm":"Base Color","np":3,"mn":"ADBE Color Control","ix":2,"en":1,"ef":[{"ty":2,"nm":"Color","mn":"ADBE Color Control-0001","ix":1,"v":{"a":0,"k":[0.019607843831,0.164705887437,0.458823531866,1],"ix":1,"x":"var $bm_rt;\n$bm_rt = effect('Base Color')('Color');"}}]},{"ty":5,"nm":"Highlight","np":3,"mn":"ADBE Color Control","ix":3,"en":1,"ef":[{"ty":2,"nm":"Color","mn":"ADBE Color Control-0001","ix":1,"v":{"a":0,"k":[0.992156863213,0.560784339905,0.003921568859,1],"ix":1}}]},{"ty":5,"nm":"Stroke width 2","np":3,"mn":"ADBE Slider Control","ix":4,"en":1,"ef":[{"ty":0,"nm":"Slider","mn":"ADBE Slider Control-0001","ix":1,"v":{"a":0,"k":18,"ix":1}}]}],"sw":100,"sh":100,"sc":"#ffffff","ip":0,"op":185,"st":0,"bm":0},{"ddd":0,"ind":2,"ty":4,"nm":"small cloud","sr":1,"ks":{"o":{"a":0,"k":100,"ix":11},"r":{"a":0,"k":0,"ix":10},"p":{"a":0,"k":[250,384.768,0],"ix":2,"l":2},"a":{"a":0,"k":[0,0,0],"ix":1,"l":2},"s":{"a":0,"k":[100,100,100],"ix":6,"l":2}},"ao":0,"shapes":[{"ty":"gr","it":[{"ty":"gr","it":[{"ind":0,"ty":"sh","ix":1,"ks":{"a":0,"k":{"i":[[0,0],[25.238,0],[3.793,-24.173]],"o":[[-3.793,-24.173],[-25.238,0],[0,0]],"v":[[49.945,5.932],[0,-36.732],[-49.945,5.932]],"c":false},"ix":2},"nm":"Path 1","mn":"ADBE Vector Shape - Group","hd":false},{"ind":1,"ty":"sh","ix":2,"ks":{"a":0,"k":{"i":[[0,0],[-9.001,-9.001],[12.648,-12.648],[0,0],[-12.648,12.648],[-11.296,-3.809]],"o":[[11.296,-3.809],[12.648,12.648],[0,0],[-12.648,-12.648],[9.001,-9.001],[0,0]],"v":[[40.19,-16.85],[73.465,-9.07],[73.465,36.732],[-73.465,36.732],[-73.465,-9.07],[-40.19,-16.85]],"c":false},"ix":2},"nm":"Path 2","mn":"ADBE Vector Shape - Group","hd":false},{"ty":"tr","p":{"a":0,"k":[0,0],"ix":2},"a":{"a":0,"k":[0,0],"ix":1},"s":{"a":1,"k":[{"i":{"x":[0.4,0.4],"y":[1,1]},"o":{"x":[0.333,0.333],"y":[0,0]},"t":23,"s":[100,100]},{"i":{"x":[0.4,0.4],"y":[1,1]},"o":{"x":[0.167,0.167],"y":[0,0]},"t":54,"s":[75,75]},{"i":{"x":[0.667,0.667],"y":[1,1]},"o":{"x":[0.167,0.167],"y":[0,0]},"t":101,"s":[75,75]},{"t":135,"s":[100,100]}],"ix":3},"r":{"a":0,"k":0,"ix":6},"o":{"a":0,"k":100,"ix":7},"sk":{"a":0,"k":0,"ix":4},"sa":{"a":0,"k":0,"ix":5},"nm":"Transform"}],"nm":"Group 1","np":2,"cix":2,"bm":0,"ix":1,"mn":"ADBE Vector Group","hd":false},{"ty":"st","c":{"a":0,"k":[0,0,0,1],"ix":3,"x":"var $bm_rt;\n$bm_rt = thisComp.layer('Main Stroke width - Color Ctrl').effect('Base Color')('Color');"},"o":{"a":0,"k":100,"ix":4},"w":{"a":0,"k":16,"ix":5,"x":"var $bm_rt;\n$bm_rt = thisComp.layer('Main Stroke width - Color Ctrl').effect('Stroke width')('Slider');"},"lc":2,"lj":2,"bm":0,"nm":"Stroke 1","mn":"ADBE Vector Graphic - Stroke","hd":false},{"ty":"tr","p":{"a":0,"k":[0,0],"ix":2},"a":{"a":0,"k":[0,0],"ix":1},"s":{"a":0,"k":[100,100],"ix":3},"r":{"a":0,"k":0,"ix":6},"o":{"a":0,"k":100,"ix":7},"sk":{"a":0,"k":0,"ix":4},"sa":{"a":0,"k":0,"ix":5},"nm":"Transform"}],"nm":"small cloud","np":2,"cix":2,"bm":0,"ix":1,"mn":"ADBE Vector Group","hd":false}],"ip":0,"op":180,"st":0,"ct":1,"bm":0},{"ddd":0,"ind":3,"ty":4,"nm":"small","sr":1,"ks":{"o":{"a":0,"k":100,"ix":11},"r":{"a":0,"k":0,"ix":10},"p":{"a":0,"k":[250,384.768,0],"ix":2,"l":2},"a":{"a":0,"k":[250,384.768,0],"ix":1,"l":2},"s":{"a":0,"k":[100,100,100],"ix":6,"l":2,"x":"var $bm_rt;\n$bm_rt = thisComp.layer('small cloud').content('small cloud').content('Group 1').transform.scale;"}},"ao":0,"shapes":[{"ty":"gr","it":[{"ind":0,"ty":"sh","ix":1,"ks":{"a":0,"k":{"i":[[0,18.854],[-2.943,7.671],[2.063,0],[9.24,-12.084],[9.001,-9.001],[-12.648,-12.648],[0,0]],"o":[[0,-8.707],[-1.998,-0.24],[-16.387,0],[-11.296,-3.809],[-12.648,12.648],[0,0],[-12.257,-12.455]],"v":[[32.332,-11.662],[36.892,-36.368],[30.797,-36.732],[-9.393,-16.85],[-42.668,-9.07],[-42.668,36.732],[52.154,36.732]],"c":true},"ix":2},"nm":"Path 1","mn":"ADBE Vector Shape - Group","hd":false},{"ty":"fl","c":{"a":0,"k":[0.858823537827,0.29411765933,0.525490224361,1],"ix":4},"o":{"a":0,"k":100,"ix":5},"r":1,"bm":0,"nm":"Fill 1","mn":"ADBE Vector Graphic - Fill","hd":false},{"ty":"tr","p":{"a":0,"k":[219.203,384.768],"ix":2},"a":{"a":0,"k":[0,0],"ix":1},"s":{"a":0,"k":[100,100],"ix":3},"r":{"a":0,"k":0,"ix":6},"o":{"a":0,"k":100,"ix":7},"sk":{"a":0,"k":0,"ix":4},"sa":{"a":0,"k":0,"ix":5},"nm":"Transform"}],"nm":"Group 1","np":2,"cix":2,"bm":0,"ix":1,"mn":"ADBE Vector Group","hd":false},{"ty":"gr","it":[{"ind":0,"ty":"sh","ix":1,"ks":{"a":0,"k":{"i":[[0,0],[12.648,12.648],[11.296,-3.809],[16.387,0],[9.24,-12.085],[9.001,-9.001],[-12.648,-12.648]],"o":[[12.648,-12.648],[-9.001,-9.001],[-9.24,-12.085],[-16.387,0],[-11.296,-3.809],[-12.648,12.648],[0,0]],"v":[[73.465,36.732],[73.465,-9.07],[40.19,-16.85],[0,-36.732],[-40.19,-16.85],[-73.465,-9.07],[-73.465,36.732]],"c":true},"ix":2},"nm":"Path 1","mn":"ADBE Vector Shape - Group","hd":false},{"ty":"fl","c":{"a":0,"k":[0.992156863213,0.376470595598,0.313725501299,1],"ix":4},"o":{"a":0,"k":100,"ix":5},"r":1,"bm":0,"nm":"Fill 1","mn":"ADBE Vector Graphic - Fill","hd":false},{"ty":"tr","p":{"a":0,"k":[250,384.768],"ix":2},"a":{"a":0,"k":[0,0],"ix":1},"s":{"a":0,"k":[100,100],"ix":3},"r":{"a":0,"k":0,"ix":6},"o":{"a":0,"k":100,"ix":7},"sk":{"a":0,"k":0,"ix":4},"sa":{"a":0,"k":0,"ix":5},"nm":"Transform"}],"nm":"Group 2","np":2,"cix":2,"bm":0,"ix":2,"mn":"ADBE Vector Group","hd":false}],"ip":0,"op":180,"st":0,"ct":1,"bm":0},{"ddd":0,"ind":4,"ty":4,"nm":"small cloud 4","td":1,"sr":1,"ks":{"o":{"a":0,"k":100,"ix":11},"r":{"a":0,"k":0,"ix":10},"p":{"a":0,"k":[250,384.768,0],"ix":2,"l":2},"a":{"a":0,"k":[0,0,0],"ix":1,"l":2},"s":{"a":0,"k":[100,100,100],"ix":6,"l":2}},"ao":0,"shapes":[{"ty":"gr","it":[{"ty":"gr","it":[{"ind":0,"ty":"sh","ix":1,"ks":{"a":0,"k":{"i":[[0,0],[-9.001,-9.001],[12.648,-12.648],[0,0],[-12.648,12.648],[-11.296,-3.809]],"o":[[11.296,-3.809],[12.648,12.648],[0,0],[-12.648,-12.648],[9.001,-9.001],[0,0]],"v":[[41.877,-16.85],[73.465,-9.07],[73.418,55.566],[-73.512,55.566],[-73.465,-9.07],[-37.877,-19.288]],"c":false},"ix":2},"nm":"Path 2","mn":"ADBE Vector Shape - Group","hd":false},{"ty":"fl","c":{"a":0,"k":[1,0,0,1],"ix":4},"o":{"a":0,"k":100,"ix":5},"r":1,"bm":0,"nm":"Fill 1","mn":"ADBE Vector Graphic - Fill","hd":false},{"ty":"tr","p":{"a":0,"k":[0,0],"ix":2},"a":{"a":0,"k":[0,0],"ix":1},"s":{"a":1,"k":[{"i":{"x":[0.4,0.4],"y":[1,1]},"o":{"x":[0.333,0.333],"y":[0,0]},"t":23,"s":[100,100]},{"i":{"x":[0.4,0.4],"y":[1,1]},"o":{"x":[0.167,0.167],"y":[0,0]},"t":54,"s":[75,75]},{"i":{"x":[0.667,0.667],"y":[1,1]},"o":{"x":[0.167,0.167],"y":[0,0]},"t":101,"s":[75,75]},{"t":135,"s":[100,100]}],"ix":3},"r":{"a":0,"k":0,"ix":6},"o":{"a":0,"k":100,"ix":7},"sk":{"a":0,"k":0,"ix":4},"sa":{"a":0,"k":0,"ix":5},"nm":"Transform"}],"nm":"Group 2","np":3,"cix":2,"bm":0,"ix":1,"mn":"ADBE Vector Group","hd":false},{"ty":"gr","it":[{"ind":0,"ty":"sh","ix":1,"ks":{"a":0,"k":{"i":[[0,0],[25.238,0],[0.695,-3.95]],"o":[[-2.445,-18.7],[-25.238,0],[0,0]],"v":[[43.445,-16.568],[0,-36.732],[-37.195,-17.318]],"c":false},"ix":2},"nm":"Path 1","mn":"ADBE Vector Shape - Group","hd":false},{"ty":"fl","c":{"a":0,"k":[1,0,0,1],"ix":4},"o":{"a":0,"k":100,"ix":5},"r":1,"bm":0,"nm":"Fill 1","mn":"ADBE Vector Graphic - Fill","hd":false},{"ty":"tr","p":{"a":0,"k":[0,0],"ix":2},"a":{"a":0,"k":[0,0],"ix":1},"s":{"a":1,"k":[{"i":{"x":[0.4,0.4],"y":[1,1]},"o":{"x":[0.333,0.333],"y":[0,0]},"t":23,"s":[100,100]},{"i":{"x":[0.4,0.4],"y":[1,1]},"o":{"x":[0.167,0.167],"y":[0,0]},"t":54,"s":[75,75]},{"i":{"x":[0.667,0.667],"y":[1,1]},"o":{"x":[0.167,0.167],"y":[0,0]},"t":101,"s":[75,75]},{"t":135,"s":[100,100]}],"ix":3},"r":{"a":0,"k":0,"ix":6},"o":{"a":0,"k":100,"ix":7},"sk":{"a":0,"k":0,"ix":4},"sa":{"a":0,"k":0,"ix":5},"nm":"Transform"}],"nm":"Group 1","np":3,"cix":2,"bm":0,"ix":2,"mn":"ADBE Vector Group","hd":false},{"ty":"tr","p":{"a":0,"k":[0,0],"ix":2},"a":{"a":0,"k":[0,0],"ix":1},"s":{"a":0,"k":[100,100],"ix":3},"r":{"a":0,"k":0,"ix":6},"o":{"a":0,"k":100,"ix":7},"sk":{"a":0,"k":0,"ix":4},"sa":{"a":0,"k":0,"ix":5},"nm":"Transform"}],"nm":"small cloud","np":3,"cix":2,"bm":0,"ix":1,"mn":"ADBE Vector Group","hd":false}],"ip":0,"op":180,"st":0,"ct":1,"bm":0},{"ddd":0,"ind":5,"ty":0,"nm":"explosion","tt":2,"tp":4,"refId":"comp_0","sr":1,"ks":{"o":{"a":0,"k":100,"ix":11},"r":{"a":0,"k":0,"ix":10},"p":{"a":0,"k":[250,250,0],"ix":2,"l":2},"a":{"a":0,"k":[250,250,0],"ix":1,"l":2},"s":{"a":0,"k":[100,100,100],"ix":6,"l":2}},"ao":0,"w":500,"h":500,"ip":0,"op":180,"st":0,"bm":0}],"markers":[{"tm":10,"cm":"1","dr":0},{"tm":44,"cm":"2","dr":0},{"tm":82,"cm":"3","dr":0},{"tm":111,"cm":"4","dr":0},{"tm":166,"cm":"FIN\r\n","dr":0}],"props":{}}