{"v":"5.10.2","fr":25,"ip":0,"op":55,"w":500,"h":500,"nm":"18 Wind Turbine","ddd":0,"assets":[],"layers":[{"ddd":0,"ind":1,"ty":3,"nm":"Main Stroke width - Color Ctrl","sr":1,"ks":{"o":{"a":0,"k":0,"ix":11},"r":{"a":0,"k":0,"ix":10},"p":{"a":0,"k":[250,250,0],"ix":2,"l":2},"a":{"a":0,"k":[50,50,0],"ix":1,"l":2},"s":{"a":0,"k":[100,100,100],"ix":6,"l":2}},"ao":0,"ef":[{"ty":5,"nm":"Stroke width","np":3,"mn":"ADBE Slider Control","ix":1,"en":1,"ef":[{"ty":0,"nm":"Slider","mn":"ADBE Slider Control-0001","ix":1,"v":{"a":0,"k":16,"ix":1}}]},{"ty":5,"nm":"Base Color","np":3,"mn":"ADBE Color Control","ix":2,"en":1,"ef":[{"ty":2,"nm":"Color","mn":"ADBE Color Control-0001","ix":1,"v":{"a":0,"k":[0.019607843831,0.164705887437,0.458823531866,1],"ix":1}}]},{"ty":5,"nm":"Highlight","np":3,"mn":"ADBE Color Control","ix":3,"en":1,"ef":[{"ty":2,"nm":"Color","mn":"ADBE Color Control-0001","ix":1,"v":{"a":0,"k":[0.992156863213,0.796078443527,0.313725501299,1],"ix":1}}]},{"ty":5,"nm":"Highlight 2","np":3,"mn":"ADBE Color Control","ix":4,"en":1,"ef":[{"ty":2,"nm":"Color","mn":"ADBE Color Control-0001","ix":1,"v":{"a":0,"k":[0.57647061348,0.698039233685,0.956862747669,1],"ix":1}}]},{"ty":5,"nm":"Stroke width details","np":3,"mn":"ADBE Slider Control","ix":5,"en":1,"ef":[{"ty":0,"nm":"Slider","mn":"ADBE Slider Control-0001","ix":1,"v":{"a":0,"k":18,"ix":1}}]}],"ip":0,"op":75.8333333333333,"st":0,"bm":0},{"ddd":0,"ind":2,"ty":4,"nm":"wind 2","sr":1,"ks":{"o":{"a":0,"k":100,"ix":11},"r":{"a":0,"k":0,"ix":10},"p":{"a":1,"k":[{"i":{"x":0.833,"y":0.833},"o":{"x":0.167,"y":0.167},"t":41,"s":[137.105,108.19,0],"to":[8.333,0,0],"ti":[-8.333,0,0]},{"t":55,"s":[187.105,108.19,0]}],"ix":2,"l":2},"a":{"a":0,"k":[187.105,108.19,0],"ix":1,"l":2},"s":{"a":0,"k":[100,100,100],"ix":6,"l":2}},"ao":0,"shapes":[{"ty":"gr","it":[{"ind":0,"ty":"sh","ix":1,"ks":{"a":0,"k":{"i":[[0,0],[0,0]],"o":[[0,0],[0,0]],"v":[[43.422,0],[-43.422,0]],"c":false},"ix":2},"nm":"Path 1","mn":"ADBE Vector Shape - Group","hd":false},{"ty":"tm","s":{"a":1,"k":[{"i":{"x":[0.833],"y":[0.833]},"o":{"x":[0.333],"y":[0]},"t":44,"s":[100]},{"t":55,"s":[0]}],"ix":1},"e":{"a":0,"k":100,"ix":2},"o":{"a":0,"k":0,"ix":3},"m":1,"ix":2,"nm":"Trim Paths 1","mn":"ADBE Vector Filter - Trim","hd":false},{"ty":"st","c":{"a":0,"k":[0,0,0,1],"ix":3,"x":"var $bm_rt;\n$bm_rt = thisComp.layer('Main Stroke width - Color Ctrl').effect('Highlight 2')('Color');"},"o":{"a":0,"k":100,"ix":4},"w":{"a":0,"k":16,"ix":5,"x":"var $bm_rt;\n$bm_rt = thisComp.layer('Main Stroke width - Color Ctrl').effect('Stroke width')('Slider');"},"lc":2,"lj":2,"bm":0,"nm":"Stroke 1","mn":"ADBE Vector Graphic - Stroke","hd":false},{"ty":"tr","p":{"a":0,"k":[164.887,137.88],"ix":2},"a":{"a":0,"k":[0,0],"ix":1},"s":{"a":0,"k":[100,100],"ix":3},"r":{"a":0,"k":0,"ix":6},"o":{"a":0,"k":100,"ix":7},"sk":{"a":0,"k":0,"ix":4},"sa":{"a":0,"k":0,"ix":5},"nm":"Transform"}],"nm":"Group 1","np":3,"cix":2,"bm":0,"ix":1,"mn":"ADBE Vector Group","hd":false},{"ty":"gr","it":[{"ind":0,"ty":"sh","ix":1,"ks":{"a":0,"k":{"i":[[0,0],[0,0],[0,8.837],[0,0],[8.724,0],[0,0]],"o":[[0,0],[8.724,0],[0,0],[0,-8.837],[0,0],[0,0]],"v":[[-46.78,16.002],[30.984,16.002],[46.78,0],[46.78,0],[30.984,-16.002],[23.836,-16.002]],"c":false},"ix":2},"nm":"Path 1","mn":"ADBE Vector Shape - Group","hd":false},{"ty":"tm","s":{"a":0,"k":0,"ix":1},"e":{"a":1,"k":[{"i":{"x":[0.833],"y":[0.833]},"o":{"x":[0.333],"y":[0]},"t":41,"s":[0]},{"t":55,"s":[100]}],"ix":2},"o":{"a":0,"k":0,"ix":3},"m":1,"ix":2,"nm":"Trim Paths 1","mn":"ADBE Vector Filter - Trim","hd":false},{"ty":"st","c":{"a":0,"k":[0,0,0,1],"ix":3,"x":"var $bm_rt;\n$bm_rt = thisComp.layer('Main Stroke width - Color Ctrl').effect('Highlight 2')('Color');"},"o":{"a":0,"k":100,"ix":4},"w":{"a":0,"k":16,"ix":5,"x":"var $bm_rt;\n$bm_rt = thisComp.layer('Main Stroke width - Color Ctrl').effect('Stroke width')('Slider');"},"lc":2,"lj":2,"bm":0,"nm":"Stroke 1","mn":"ADBE Vector Graphic - Stroke","hd":false},{"ty":"tr","p":{"a":0,"k":[205.964,94.502],"ix":2},"a":{"a":0,"k":[0,0],"ix":1},"s":{"a":0,"k":[100,100],"ix":3},"r":{"a":0,"k":0,"ix":6},"o":{"a":0,"k":100,"ix":7},"sk":{"a":0,"k":0,"ix":4},"sa":{"a":0,"k":0,"ix":5},"nm":"Transform"}],"nm":"Group 2","np":3,"cix":2,"bm":0,"ix":2,"mn":"ADBE Vector Group","hd":false}],"ip":9,"op":70,"st":-5,"ct":1,"bm":0},{"ddd":0,"ind":3,"ty":4,"nm":"wind","sr":1,"ks":{"o":{"a":0,"k":100,"ix":11},"r":{"a":0,"k":0,"ix":10},"p":{"a":1,"k":[{"i":{"x":0.833,"y":0.833},"o":{"x":0.167,"y":0.167},"t":0,"s":[187.105,108.19,0],"to":[8.333,0,0],"ti":[-8.333,0,0]},{"t":14,"s":[237.105,108.19,0]}],"ix":2,"l":2},"a":{"a":0,"k":[187.105,108.19,0],"ix":1,"l":2},"s":{"a":0,"k":[100,100,100],"ix":6,"l":2}},"ao":0,"shapes":[{"ty":"gr","it":[{"ind":0,"ty":"sh","ix":1,"ks":{"a":0,"k":{"i":[[0,0],[0,0]],"o":[[0,0],[0,0]],"v":[[43.422,0],[-43.422,0]],"c":false},"ix":2},"nm":"Path 1","mn":"ADBE Vector Shape - Group","hd":false},{"ty":"tm","s":{"a":0,"k":0,"ix":1},"e":{"a":1,"k":[{"i":{"x":[0.667],"y":[1]},"o":{"x":[0.167],"y":[0.167]},"t":0,"s":[100]},{"t":11,"s":[0]}],"ix":2},"o":{"a":0,"k":0,"ix":3},"m":1,"ix":2,"nm":"Trim Paths 1","mn":"ADBE Vector Filter - Trim","hd":false},{"ty":"st","c":{"a":0,"k":[0,0,0,1],"ix":3,"x":"var $bm_rt;\n$bm_rt = thisComp.layer('Main Stroke width - Color Ctrl').effect('Highlight 2')('Color');"},"o":{"a":0,"k":100,"ix":4},"w":{"a":0,"k":16,"ix":5,"x":"var $bm_rt;\n$bm_rt = thisComp.layer('Main Stroke width - Color Ctrl').effect('Stroke width')('Slider');"},"lc":2,"lj":2,"bm":0,"nm":"Stroke 1","mn":"ADBE Vector Graphic - Stroke","hd":false},{"ty":"tr","p":{"a":0,"k":[164.887,137.88],"ix":2},"a":{"a":0,"k":[0,0],"ix":1},"s":{"a":0,"k":[100,100],"ix":3},"r":{"a":0,"k":0,"ix":6},"o":{"a":0,"k":100,"ix":7},"sk":{"a":0,"k":0,"ix":4},"sa":{"a":0,"k":0,"ix":5},"nm":"Transform"}],"nm":"Group 1","np":3,"cix":2,"bm":0,"ix":1,"mn":"ADBE Vector Group","hd":false},{"ty":"gr","it":[{"ind":0,"ty":"sh","ix":1,"ks":{"a":0,"k":{"i":[[0,0],[0,0],[0,8.837],[0,0],[8.724,0],[0,0]],"o":[[0,0],[8.724,0],[0,0],[0,-8.837],[0,0],[0,0]],"v":[[-46.78,16.002],[30.984,16.002],[46.78,0],[46.78,0],[30.984,-16.002],[23.836,-16.002]],"c":false},"ix":2},"nm":"Path 1","mn":"ADBE Vector Shape - Group","hd":false},{"ty":"tm","s":{"a":1,"k":[{"i":{"x":[0.667],"y":[1]},"o":{"x":[0.167],"y":[0.167]},"t":0,"s":[0]},{"t":14,"s":[100]}],"ix":1},"e":{"a":0,"k":100,"ix":2},"o":{"a":0,"k":0,"ix":3},"m":1,"ix":2,"nm":"Trim Paths 1","mn":"ADBE Vector Filter - Trim","hd":false},{"ty":"st","c":{"a":0,"k":[0,0,0,1],"ix":3,"x":"var $bm_rt;\n$bm_rt = thisComp.layer('Main Stroke width - Color Ctrl').effect('Highlight 2')('Color');"},"o":{"a":0,"k":100,"ix":4},"w":{"a":0,"k":16,"ix":5,"x":"var $bm_rt;\n$bm_rt = thisComp.layer('Main Stroke width - Color Ctrl').effect('Stroke width')('Slider');"},"lc":2,"lj":2,"bm":0,"nm":"Stroke 1","mn":"ADBE Vector Graphic - Stroke","hd":false},{"ty":"tr","p":{"a":0,"k":[205.964,94.502],"ix":2},"a":{"a":0,"k":[0,0],"ix":1},"s":{"a":0,"k":[100,100],"ix":3},"r":{"a":0,"k":0,"ix":6},"o":{"a":0,"k":100,"ix":7},"sk":{"a":0,"k":0,"ix":4},"sa":{"a":0,"k":0,"ix":5},"nm":"Transform"}],"nm":"Group 2","np":3,"cix":2,"bm":0,"ix":2,"mn":"ADBE Vector Group","hd":false}],"ip":0,"op":14,"st":0,"ct":1,"bm":0},{"ddd":0,"ind":4,"ty":4,"nm":"base","sr":1,"ks":{"o":{"a":0,"k":100,"ix":11},"r":{"a":0,"k":0,"ix":10},"p":{"a":0,"k":[250,421.5,0],"ix":2,"l":2},"a":{"a":0,"k":[0,0,0],"ix":1,"l":2},"s":{"a":0,"k":[100,100,100],"ix":6,"l":2}},"ao":0,"shapes":[{"ty":"gr","it":[{"ind":0,"ty":"sh","ix":1,"ks":{"a":0,"k":{"i":[[0,0],[0,0]],"o":[[0,0],[0,0]],"v":[[-171.5,0],[171.5,0]],"c":false},"ix":2},"nm":"Path 1","mn":"ADBE Vector Shape - Group","hd":false},{"ty":"st","c":{"a":0,"k":[0,0,0,1],"ix":3,"x":"var $bm_rt;\n$bm_rt = thisComp.layer('Main Stroke width - Color Ctrl').effect('Base Color')('Color');"},"o":{"a":0,"k":100,"ix":4},"w":{"a":0,"k":16,"ix":5,"x":"var $bm_rt;\n$bm_rt = thisComp.layer('Main Stroke width - Color Ctrl').effect('Stroke width')('Slider');"},"lc":2,"lj":2,"bm":0,"nm":"Stroke 1","mn":"ADBE Vector Graphic - Stroke","hd":false},{"ty":"tr","p":{"a":0,"k":[0,0],"ix":2},"a":{"a":0,"k":[0,0],"ix":1},"s":{"a":0,"k":[100,100],"ix":3},"r":{"a":0,"k":0,"ix":6},"o":{"a":0,"k":100,"ix":7},"sk":{"a":0,"k":0,"ix":4},"sa":{"a":0,"k":0,"ix":5},"nm":"Transform"}],"nm":"Group 1","np":2,"cix":2,"bm":0,"ix":1,"mn":"ADBE Vector Group","hd":false}],"ip":0,"op":75,"st":0,"ct":1,"bm":0},{"ddd":0,"ind":5,"ty":4,"nm":"mill-R","sr":1,"ks":{"o":{"a":0,"k":100,"ix":11},"r":{"a":1,"k":[{"i":{"x":[0.42],"y":[1]},"o":{"x":[0.58],"y":[0]},"t":0,"s":[0]},{"t":41,"s":[360]}],"ix":10},"p":{"a":0,"k":[316.583,184.403,0],"ix":2,"l":2},"a":{"a":0,"k":[316.583,184.403,0],"ix":1,"l":2},"s":{"a":0,"k":[100,100,100],"ix":6,"l":2}},"ao":0,"shapes":[{"ty":"gr","it":[{"ind":0,"ty":"sh","ix":1,"ks":{"a":0,"k":{"i":[[0,-9.803],[-9.803,0],[0,9.803],[9.803,0]],"o":[[0,9.803],[9.803,0],[0,-9.803],[-9.803,0]],"v":[[-17.751,0],[0,17.751],[17.751,0],[0,-17.751]],"c":true},"ix":2},"nm":"Path 1","mn":"ADBE Vector Shape - Group","hd":false},{"ty":"st","c":{"a":0,"k":[0.20000000298,0.800000011921,0.800000011921,1],"ix":3,"x":"var $bm_rt;\n$bm_rt = thisComp.layer('Main Stroke width - Color Ctrl').effect('Base Color')('Color');"},"o":{"a":0,"k":100,"ix":4},"w":{"a":0,"k":16,"ix":5,"x":"var $bm_rt;\n$bm_rt = thisComp.layer('Main Stroke width - Color Ctrl').effect('Stroke width')('Slider');"},"lc":2,"lj":2,"bm":0,"nm":"Stroke 1","mn":"ADBE Vector Graphic - Stroke","hd":false},{"ty":"tr","p":{"a":0,"k":[316.583,184.521],"ix":2},"a":{"a":0,"k":[0,0],"ix":1},"s":{"a":0,"k":[100,100],"ix":3},"r":{"a":0,"k":0,"ix":6},"o":{"a":0,"k":100,"ix":7},"sk":{"a":0,"k":0,"ix":4},"sa":{"a":0,"k":0,"ix":5},"nm":"Transform"}],"nm":"Group 1","np":2,"cix":2,"bm":0,"ix":1,"mn":"ADBE Vector Group","hd":false},{"ty":"gr","it":[{"ind":0,"ty":"sh","ix":1,"ks":{"a":0,"k":{"i":[[0,0],[0,0],[11.507,-12.135],[0,0],[1.59,-8.497],[0,0],[0,0],[-8.406,2.015],[0,0],[-12.253,11.381],[0,0]],"o":[[0,0],[-15.983,4.921],[0,0],[-5.948,6.273],[0,0],[0,0],[8.153,2.872],[0,0],[16.263,-3.898],[0,0],[0,0]],"v":[[29.802,-30.978],[10.617,-25.07],[-31.316,0.947],[-31.316,0.947],[-42.864,23.574],[-43.543,27.203],[-40.061,28.429],[-14.692,29.742],[-14.692,29.742],[28.807,6.435],[43.543,-7.251]],"c":false},"ix":2},"nm":"Path 1","mn":"ADBE Vector Shape - Group","hd":false},{"ty":"st","c":{"a":0,"k":[0.20000000298,0.800000011921,0.800000011921,1],"ix":3,"x":"var $bm_rt;\n$bm_rt = thisComp.layer('Main Stroke width - Color Ctrl').effect('Base Color')('Color');"},"o":{"a":0,"k":100,"ix":4},"w":{"a":0,"k":16,"ix":5,"x":"var $bm_rt;\n$bm_rt = thisComp.layer('Main Stroke width - Color Ctrl').effect('Stroke width')('Slider');"},"lc":2,"lj":2,"bm":0,"nm":"Stroke 1","mn":"ADBE Vector Graphic - Stroke","hd":false},{"ty":"tr","p":{"a":0,"k":[268.31,210.329],"ix":2},"a":{"a":0,"k":[0,0],"ix":1},"s":{"a":0,"k":[100,100],"ix":3},"r":{"a":0,"k":0,"ix":6},"o":{"a":0,"k":100,"ix":7},"sk":{"a":0,"k":0,"ix":4},"sa":{"a":0,"k":0,"ix":5},"nm":"Transform"}],"nm":"Group 2","np":2,"cix":2,"bm":0,"ix":2,"mn":"ADBE Vector Group","hd":false},{"ty":"gr","it":[{"ind":0,"ty":"sh","ix":1,"ks":{"a":0,"k":{"i":[[0,0],[0,0],[-16.263,-3.898],[0,0],[-8.153,2.872],[0,0],[0,0],[5.948,6.273],[0,0],[15.983,4.921],[0,0]],"o":[[0,0],[12.253,11.381],[0,0],[8.406,2.015],[0,0],[0,0],[-1.59,-8.497],[0,0],[-11.507,-12.135],[0,0],[0,0]],"v":[[-43.567,-7.296],[-28.783,6.435],[14.716,29.742],[14.716,29.742],[40.085,28.429],[43.567,27.203],[42.888,23.574],[31.34,0.947],[31.34,0.947],[-10.593,-25.07],[-29.778,-30.978]],"c":false},"ix":2},"nm":"Path 1","mn":"ADBE Vector Shape - Group","hd":false},{"ty":"st","c":{"a":0,"k":[0.20000000298,0.800000011921,0.800000011921,1],"ix":3,"x":"var $bm_rt;\n$bm_rt = thisComp.layer('Main Stroke width - Color Ctrl').effect('Base Color')('Color');"},"o":{"a":0,"k":100,"ix":4},"w":{"a":0,"k":16,"ix":5,"x":"var $bm_rt;\n$bm_rt = thisComp.layer('Main Stroke width - Color Ctrl').effect('Stroke width')('Slider');"},"lc":2,"lj":2,"bm":0,"nm":"Stroke 1","mn":"ADBE Vector Graphic - Stroke","hd":false},{"ty":"tr","p":{"a":0,"k":[364.833,210.329],"ix":2},"a":{"a":0,"k":[0,0],"ix":1},"s":{"a":0,"k":[100,100],"ix":3},"r":{"a":0,"k":0,"ix":6},"o":{"a":0,"k":100,"ix":7},"sk":{"a":0,"k":0,"ix":4},"sa":{"a":0,"k":0,"ix":5},"nm":"Transform"}],"nm":"Group 3","np":2,"cix":2,"bm":0,"ix":3,"mn":"ADBE Vector Group","hd":false},{"ty":"gr","it":[{"ind":0,"ty":"sh","ix":1,"ks":{"a":0,"k":{"i":[[0,0],[0,0],[4.756,16.033],[0,0],[6.564,5.625],[0,0],[0,0],[2.458,-8.287],[0,0],[-3.729,-16.302],[0,0]],"o":[[0,0],[3.729,-16.302],[0,0],[-2.458,-8.287],[0,0],[0,0],[-6.564,5.625],[0,0],[-4.756,16.033],[0,0],[0,0]],"v":[[13.593,46.567],[18.19,26.473],[16.624,-22.85],[16.624,-22.85],[2.803,-44.164],[0,-46.567],[-2.803,-44.164],[-16.624,-22.85],[-16.624,-22.85],[-18.19,26.473],[-13.593,46.567]],"c":false},"ix":2},"nm":"Path 1","mn":"ADBE Vector Shape - Group","hd":false},{"ty":"st","c":{"a":0,"k":[0.20000000298,0.800000011921,0.800000011921,1],"ix":3,"x":"var $bm_rt;\n$bm_rt = thisComp.layer('Main Stroke width - Color Ctrl').effect('Base Color')('Color');"},"o":{"a":0,"k":100,"ix":4},"w":{"a":0,"k":16,"ix":5,"x":"var $bm_rt;\n$bm_rt = thisComp.layer('Main Stroke width - Color Ctrl').effect('Stroke width')('Slider');"},"lc":2,"lj":2,"bm":0,"nm":"Stroke 1","mn":"ADBE Vector Graphic - Stroke","hd":false},{"ty":"tr","p":{"a":0,"k":[316.583,125.067],"ix":2},"a":{"a":0,"k":[0,0],"ix":1},"s":{"a":0,"k":[100,100],"ix":3},"r":{"a":0,"k":0,"ix":6},"o":{"a":0,"k":100,"ix":7},"sk":{"a":0,"k":0,"ix":4},"sa":{"a":0,"k":0,"ix":5},"nm":"Transform"}],"nm":"Group 4","np":2,"cix":2,"bm":0,"ix":4,"mn":"ADBE Vector Group","hd":false}],"ip":0,"op":75,"st":0,"ct":1,"bm":0},{"ddd":0,"ind":6,"ty":4,"nm":"mill-R","parent":5,"sr":1,"ks":{"o":{"a":0,"k":100,"ix":11},"r":{"a":0,"k":0,"ix":10},"p":{"a":0,"k":[316.855,159.535,0],"ix":2,"l":2},"a":{"a":0,"k":[316.855,159.535,0],"ix":1,"l":2},"s":{"a":0,"k":[100,100,100],"ix":6,"l":2}},"ao":0,"shapes":[{"ty":"gr","it":[{"ind":0,"ty":"sh","ix":1,"ks":{"a":0,"k":{"i":[[9.828,0],[0,9.828],[-9.828,0],[0,-9.828]],"o":[[-9.828,0],[0,-9.828],[9.828,0],[0,9.828]],"v":[[0,17.823],[-17.823,0],[0,-17.823],[17.823,0]],"c":true},"ix":2},"nm":"Path 1","mn":"ADBE Vector Shape - Group","hd":false},{"ty":"fl","c":{"a":0,"k":[0.57647061348,0.698039233685,0.956862747669,1],"ix":4},"o":{"a":0,"k":100,"ix":5},"r":1,"bm":0,"nm":"Fill 1","mn":"ADBE Vector Graphic - Fill","hd":false},{"ty":"tr","p":{"a":0,"k":[316.855,184.254],"ix":2},"a":{"a":0,"k":[0,0],"ix":1},"s":{"a":0,"k":[100,100],"ix":3},"r":{"a":0,"k":0,"ix":6},"o":{"a":0,"k":100,"ix":7},"sk":{"a":0,"k":0,"ix":4},"sa":{"a":0,"k":0,"ix":5},"nm":"Transform"}],"nm":"Group 1","np":2,"cix":2,"bm":0,"ix":1,"mn":"ADBE Vector Group","hd":false},{"ty":"gr","it":[{"ind":0,"ty":"sh","ix":1,"ks":{"a":0,"k":{"i":[[0,0],[2.575,-1.041],[-11.104,-7.638],[-2.042,1.897],[0,0],[0,0]],"o":[[-2.667,0.821],[1.093,14.191],[2.187,-1.708],[0,0],[0,0],[0,0]],"v":[[-13.996,-14.985],[-21.857,-12.179],[-2.085,22.049],[4.268,16.649],[21.857,0.313],[8.947,-22.049]],"c":true},"ix":2},"nm":"Path 1","mn":"ADBE Vector Shape - Group","hd":false},{"ty":"fl","c":{"a":0,"k":[0.992156863213,0.560784339905,0.003921568859,1],"ix":4},"o":{"a":0,"k":100,"ix":5},"r":1,"bm":0,"nm":"Fill 1","mn":"ADBE Vector Graphic - Fill","hd":false},{"ty":"tr","p":{"a":0,"k":[293.04,199.979],"ix":2},"a":{"a":0,"k":[0,0],"ix":1},"s":{"a":0,"k":[100,100],"ix":3},"r":{"a":0,"k":0,"ix":6},"o":{"a":0,"k":100,"ix":7},"sk":{"a":0,"k":0,"ix":4},"sa":{"a":0,"k":0,"ix":5},"nm":"Transform"}],"nm":"Group 2","np":2,"cix":2,"bm":0,"ix":2,"mn":"ADBE Vector Group","hd":false},{"ty":"gr","it":[{"ind":0,"ty":"sh","ix":1,"ks":{"a":0,"k":{"i":[[0,0],[0,0],[0,0],[11.554,-12.185],[0,0],[1.596,-8.532],[0,0],[0,0],[-8.441,2.023],[0,0],[-12.303,11.427]],"o":[[0,0],[0,0],[-16.048,4.941],[0,0],[-5.972,6.298],[0,0],[0,0],[8.187,2.883],[0,0],[16.329,-3.914],[0,0]],"v":[[45.117,-9.308],[32.206,-31.671],[9.264,-24.606],[-32.84,1.518],[-32.84,1.518],[-44.435,24.237],[-45.117,27.88],[-41.621,29.112],[-16.148,30.429],[-16.148,30.429],[27.528,7.028]],"c":true},"ix":2},"nm":"Path 1","mn":"ADBE Vector Shape - Group","hd":false},{"ty":"fl","c":{"a":0,"k":[0.992156863213,0.796078443527,0.313725501299,1],"ix":4},"o":{"a":0,"k":100,"ix":5},"r":1,"bm":0,"nm":"Fill 1","mn":"ADBE Vector Graphic - Fill","hd":false},{"ty":"tr","p":{"a":0,"k":[269.781,209.6],"ix":2},"a":{"a":0,"k":[0,0],"ix":1},"s":{"a":0,"k":[100,100],"ix":3},"r":{"a":0,"k":0,"ix":6},"o":{"a":0,"k":100,"ix":7},"sk":{"a":0,"k":0,"ix":4},"sa":{"a":0,"k":0,"ix":5},"nm":"Transform"}],"nm":"Group 3","np":2,"cix":2,"bm":0,"ix":3,"mn":"ADBE Vector Group","hd":false},{"ty":"gr","it":[{"ind":0,"ty":"sh","ix":1,"ks":{"a":0,"k":{"i":[[2.667,0.821],[0,0],[0,0],[0,0],[-2.187,-1.708],[-1.093,14.191]],"o":[[0,0],[0,0],[0,0],[2.042,1.897],[11.104,-7.638],[-2.575,-1.041]],"v":[[13.996,-14.985],[-8.947,-22.049],[-21.858,0.313],[-4.269,16.649],[2.085,22.049],[21.858,-12.179]],"c":true},"ix":2},"nm":"Path 1","mn":"ADBE Vector Shape - Group","hd":false},{"ty":"fl","c":{"a":0,"k":[0.992156863213,0.560784339905,0.003921568859,1],"ix":4},"o":{"a":0,"k":100,"ix":5},"r":1,"bm":0,"nm":"Fill 1","mn":"ADBE Vector Graphic - Fill","hd":false},{"ty":"tr","p":{"a":0,"k":[340.671,199.979],"ix":2},"a":{"a":0,"k":[0,0],"ix":1},"s":{"a":0,"k":[100,100],"ix":3},"r":{"a":0,"k":0,"ix":6},"o":{"a":0,"k":100,"ix":7},"sk":{"a":0,"k":0,"ix":4},"sa":{"a":0,"k":0,"ix":5},"nm":"Transform"}],"nm":"Group 4","np":2,"cix":2,"bm":0,"ix":4,"mn":"ADBE Vector Group","hd":false},{"ty":"gr","it":[{"ind":0,"ty":"sh","ix":1,"ks":{"a":0,"k":{"i":[[0,0],[0,0],[0,0],[-16.329,-3.914],[0,0],[-8.187,2.883],[0,0],[0,0],[5.972,6.298],[0,0],[16.048,4.941]],"o":[[0,0],[0,0],[12.303,11.427],[0,0],[8.441,2.023],[0,0],[0,0],[-1.596,-8.532],[0,0],[-11.554,-12.185],[0,0]],"v":[[-32.206,-31.671],[-45.117,-9.308],[-27.528,7.028],[16.148,30.429],[16.148,30.429],[41.621,29.112],[45.117,27.88],[44.435,24.237],[32.84,1.518],[32.84,1.518],[-9.264,-24.606]],"c":true},"ix":2},"nm":"Path 1","mn":"ADBE Vector Shape - Group","hd":false},{"ty":"fl","c":{"a":0,"k":[0.992156863213,0.796078443527,0.313725501299,1],"ix":4},"o":{"a":0,"k":100,"ix":5},"r":1,"bm":0,"nm":"Fill 1","mn":"ADBE Vector Graphic - Fill","hd":false},{"ty":"tr","p":{"a":0,"k":[363.93,209.6],"ix":2},"a":{"a":0,"k":[0,0],"ix":1},"s":{"a":0,"k":[100,100],"ix":3},"r":{"a":0,"k":0,"ix":6},"o":{"a":0,"k":100,"ix":7},"sk":{"a":0,"k":0,"ix":4},"sa":{"a":0,"k":0,"ix":5},"nm":"Transform"}],"nm":"Group 5","np":2,"cix":2,"bm":0,"ix":5,"mn":"ADBE Vector Group","hd":false},{"ty":"gr","it":[{"ind":0,"ty":"sh","ix":1,"ks":{"a":0,"k":{"i":[[7.074,0],[5.988,-2.875],[-0.623,-2.723],[0,0],[0,0],[0,0],[-0.386,2.754]],"o":[[-7.074,0],[0.386,2.754],[0,0],[0,0],[0,0],[0.623,-2.723],[-5.988,-2.875]],"v":[[0,-18.054],[-19.766,-13.566],[-18.264,-5.346],[-12.911,18.054],[12.911,18.054],[18.264,-5.346],[19.766,-13.566]],"c":true},"ix":2},"nm":"Path 1","mn":"ADBE Vector Shape - Group","hd":false},{"ty":"fl","c":{"a":0,"k":[0.992156863213,0.560784339905,0.003921568859,1],"ix":4},"o":{"a":0,"k":100,"ix":5},"r":1,"bm":0,"nm":"Fill 1","mn":"ADBE Vector Graphic - Fill","hd":false},{"ty":"tr","p":{"a":0,"k":[316.855,156.485],"ix":2},"a":{"a":0,"k":[0,0],"ix":1},"s":{"a":0,"k":[100,100],"ix":3},"r":{"a":0,"k":0,"ix":6},"o":{"a":0,"k":100,"ix":7},"sk":{"a":0,"k":0,"ix":4},"sa":{"a":0,"k":0,"ix":5},"nm":"Transform"}],"nm":"Group 6","np":2,"cix":2,"bm":0,"ix":6,"mn":"ADBE Vector Group","hd":false},{"ty":"gr","it":[{"ind":0,"ty":"sh","ix":1,"ks":{"a":0,"k":{"i":[[0,0],[0,0],[0,0],[4.775,16.098],[0,0],[6.59,5.648],[0,0],[0,0],[2.468,-8.321],[0,0],[-3.745,-16.369]],"o":[[0,0],[0,0],[3.745,-16.369],[0,0],[-2.468,-8.321],[0,0],[0,0],[-6.59,5.648],[0,0],[-4.775,16.098],[0,0]],"v":[[-12.911,48.37],[12.911,48.37],[18.264,24.969],[16.692,-24.556],[16.692,-24.556],[2.815,-45.957],[0,-48.37],[-2.815,-45.957],[-16.692,-24.556],[-16.692,-24.556],[-18.264,24.969]],"c":true},"ix":2},"nm":"Path 1","mn":"ADBE Vector Shape - Group","hd":false},{"ty":"fl","c":{"a":0,"k":[0.992156863213,0.796078443527,0.313725501299,1],"ix":4},"o":{"a":0,"k":100,"ix":5},"r":1,"bm":0,"nm":"Fill 1","mn":"ADBE Vector Graphic - Fill","hd":false},{"ty":"tr","p":{"a":0,"k":[316.855,126.17],"ix":2},"a":{"a":0,"k":[0,0],"ix":1},"s":{"a":0,"k":[100,100],"ix":3},"r":{"a":0,"k":0,"ix":6},"o":{"a":0,"k":100,"ix":7},"sk":{"a":0,"k":0,"ix":4},"sa":{"a":0,"k":0,"ix":5},"nm":"Transform"}],"nm":"Group 7","np":2,"cix":2,"bm":0,"ix":7,"mn":"ADBE Vector Group","hd":false}],"ip":0,"op":75,"st":0,"ct":1,"bm":0},{"ddd":0,"ind":7,"ty":4,"nm":"right","sr":1,"ks":{"o":{"a":0,"k":100,"ix":11},"r":{"a":0,"k":0,"ix":10},"p":{"a":0,"k":[320.785,310.859,0],"ix":2,"l":2},"a":{"a":0,"k":[320.785,310.859,0],"ix":1,"l":2},"s":{"a":0,"k":[100,100,100],"ix":6,"l":2}},"ao":0,"shapes":[{"ty":"gr","it":[{"ind":0,"ty":"sh","ix":1,"ks":{"a":0,"k":{"i":[[0,0],[0,9.973],[-8.363,1.578],[0,2.141],[-9.973,0],[-1.451,-0.376],[-8.163,0],[-2.235,-7.435],[-1.569,0],[0,-9.973],[0.684,-1.906],[0,-8.822],[9.973,0]],"o":[[-9.973,0],[0,-8.822],[-0.684,-1.906],[0,-9.973],[1.569,0],[2.235,-7.435],[8.163,0],[1.451,-0.376],[9.973,0],[0,2.141],[8.363,1.578],[0,9.973],[0,0]],"v":[[-35.467,36.116],[-53.524,18.058],[-38.833,0.318],[-39.893,-5.783],[-21.835,-23.84],[-17.293,-23.264],[0,-36.116],[17.293,-23.264],[21.835,-23.84],[39.893,-5.783],[38.833,0.318],[53.524,18.058],[35.467,36.116]],"c":false},"ix":2},"nm":"Path 1","mn":"ADBE Vector Shape - Group","hd":false},{"ty":"st","c":{"a":0,"k":[0.20000000298,0.800000011921,0.800000011921,1],"ix":3,"x":"var $bm_rt;\n$bm_rt = thisComp.layer('Main Stroke width - Color Ctrl').effect('Base Color')('Color');"},"o":{"a":0,"k":100,"ix":4},"w":{"a":0,"k":16,"ix":5,"x":"var $bm_rt;\n$bm_rt = thisComp.layer('Main Stroke width - Color Ctrl').effect('Stroke width')('Slider');"},"lc":2,"lj":2,"bm":0,"nm":"Stroke 1","mn":"ADBE Vector Graphic - Stroke","hd":false},{"ty":"tr","p":{"a":0,"k":[298.833,385.384],"ix":2},"a":{"a":0,"k":[0,0],"ix":1},"s":{"a":0,"k":[100,100],"ix":3},"r":{"a":0,"k":0,"ix":6},"o":{"a":0,"k":100,"ix":7},"sk":{"a":0,"k":0,"ix":4},"sa":{"a":0,"k":0,"ix":5},"nm":"Transform"}],"nm":"Group 1","np":2,"cix":2,"bm":0,"ix":1,"mn":"ADBE Vector Group","hd":false},{"ty":"gr","it":[{"ind":0,"ty":"sh","ix":1,"ks":{"a":0,"k":{"i":[[0,0],[0,0]],"o":[[0,0],[0,0]],"v":[[3.882,84.721],[-3.882,-84.721]],"c":false},"ix":2},"nm":"Path 1","mn":"ADBE Vector Shape - Group","hd":false},{"ty":"st","c":{"a":0,"k":[0,0,0,1],"ix":3,"x":"var $bm_rt;\n$bm_rt = thisComp.layer('Main Stroke width - Color Ctrl').effect('Base Color')('Color');"},"o":{"a":0,"k":100,"ix":4},"w":{"a":0,"k":16,"ix":5,"x":"var $bm_rt;\n$bm_rt = thisComp.layer('Main Stroke width - Color Ctrl').effect('Stroke width')('Slider');"},"lc":2,"lj":2,"bm":0,"nm":"Stroke 1","mn":"ADBE Vector Graphic - Stroke","hd":false},{"ty":"tr","p":{"a":0,"k":[333.491,284.939],"ix":2},"a":{"a":0,"k":[0,0],"ix":1},"s":{"a":0,"k":[100,100],"ix":3},"r":{"a":0,"k":0,"ix":6},"o":{"a":0,"k":100,"ix":7},"sk":{"a":0,"k":0,"ix":4},"sa":{"a":0,"k":0,"ix":5},"nm":"Transform"}],"nm":"Group 2","np":2,"cix":2,"bm":0,"ix":2,"mn":"ADBE Vector Group","hd":false},{"ty":"gr","it":[{"ind":0,"ty":"sh","ix":1,"ks":{"a":0,"k":{"i":[[0,0],[0,0]],"o":[[0,0],[0,0]],"v":[[2.353,-73.243],[-2.353,73.243]],"c":false},"ix":2},"nm":"Path 1","mn":"ADBE Vector Shape - Group","hd":false},{"ty":"st","c":{"a":0,"k":[0,0,0,1],"ix":3,"x":"var $bm_rt;\n$bm_rt = thisComp.layer('Main Stroke width - Color Ctrl').effect('Base Color')('Color');"},"o":{"a":0,"k":100,"ix":4},"w":{"a":0,"k":16,"ix":5,"x":"var $bm_rt;\n$bm_rt = thisComp.layer('Main Stroke width - Color Ctrl').effect('Stroke width')('Slider');"},"lc":2,"lj":2,"bm":0,"nm":"Stroke 1","mn":"ADBE Vector Graphic - Stroke","hd":false},{"ty":"tr","p":{"a":0,"k":[299.081,274.243],"ix":2},"a":{"a":0,"k":[0,0],"ix":1},"s":{"a":0,"k":[100,100],"ix":3},"r":{"a":0,"k":0,"ix":6},"o":{"a":0,"k":100,"ix":7},"sk":{"a":0,"k":0,"ix":4},"sa":{"a":0,"k":0,"ix":5},"nm":"Transform"}],"nm":"Group 3","np":2,"cix":2,"bm":0,"ix":3,"mn":"ADBE Vector Group","hd":false},{"ty":"gr","it":[{"ind":0,"ty":"sh","ix":1,"ks":{"a":0,"k":{"i":[[0,0],[-5.137,0],[-1.876,-6.239],[-1.316,0],[0,-8.369],[0.574,-1.599],[0,-7.403],[8.369,0]],"o":[[2.739,-3.91],[6.85,0],[1.218,-0.316],[8.369,0],[0,1.797],[7.018,1.324],[0,8.369],[0,0]],"v":[[-28.664,-23.838],[-16.249,-30.306],[-1.739,-19.521],[2.073,-20.005],[17.226,-4.852],[16.337,0.267],[28.664,15.153],[13.512,30.306]],"c":false},"ix":2},"nm":"Path 1","mn":"ADBE Vector Shape - Group","hd":false},{"ty":"st","c":{"a":0,"k":[0.20000000298,0.800000011921,0.800000011921,1],"ix":3,"x":"var $bm_rt;\n$bm_rt = thisComp.layer('Main Stroke width - Color Ctrl').effect('Base Color')('Color');"},"o":{"a":0,"k":100,"ix":4},"w":{"a":0,"k":16,"ix":5,"x":"var $bm_rt;\n$bm_rt = thisComp.layer('Main Stroke width - Color Ctrl').effect('Stroke width')('Slider');"},"lc":2,"lj":2,"bm":0,"nm":"Stroke 1","mn":"ADBE Vector Graphic - Stroke","hd":false},{"ty":"tr","p":{"a":0,"k":[367.597,391.194],"ix":2},"a":{"a":0,"k":[0,0],"ix":1},"s":{"a":0,"k":[100,100],"ix":3},"r":{"a":0,"k":0,"ix":6},"o":{"a":0,"k":100,"ix":7},"sk":{"a":0,"k":0,"ix":4},"sa":{"a":0,"k":0,"ix":5},"nm":"Transform"}],"nm":"Group 4","np":2,"cix":2,"bm":0,"ix":4,"mn":"ADBE Vector Group","hd":false}],"ip":0,"op":75,"st":0,"ct":1,"bm":0},{"ddd":0,"ind":8,"ty":4,"nm":"right","sr":1,"ks":{"o":{"a":0,"k":100,"ix":11},"r":{"a":0,"k":0,"ix":10},"p":{"a":0,"k":[321.074,302.078,0],"ix":2,"l":2},"a":{"a":0,"k":[321.074,302.078,0],"ix":1,"l":2},"s":{"a":0,"k":[100,100,100],"ix":6,"l":2}},"ao":0,"shapes":[{"ty":"gr","it":[{"ind":0,"ty":"sh","ix":1,"ks":{"a":0,"k":{"i":[[0,0],[0,10.014],[-8.397,1.584],[0,2.15],[-10.014,0],[-1.457,-0.378],[-8.196,0],[-2.244,-7.465],[-1.575,0],[0,-10.014],[0.687,-1.914],[0,-8.858],[10.014,0]],"o":[[-10.014,0],[0,-8.858],[-0.687,-1.914],[0,-10.014],[1.575,0],[2.244,-7.465],[8.196,0],[1.457,-0.378],[10.014,0],[0,2.15],[8.397,1.584],[0,10.014],[0,0]],"v":[[-35.611,36.263],[-53.743,18.132],[-38.992,0.32],[-40.055,-5.806],[-21.924,-23.938],[-17.363,-23.359],[0,-36.263],[17.363,-23.359],[21.924,-23.938],[40.055,-5.806],[38.992,0.32],[53.743,18.132],[35.611,36.263]],"c":true},"ix":2},"nm":"Path 1","mn":"ADBE Vector Shape - Group","hd":false},{"ty":"fl","c":{"a":0,"k":[0.694117665291,0.850980401039,0.321568638086,1],"ix":4},"o":{"a":0,"k":100,"ix":5},"r":1,"bm":0,"nm":"Fill 1","mn":"ADBE Vector Graphic - Fill","hd":false},{"ty":"tr","p":{"a":0,"k":[299.032,385.937],"ix":2},"a":{"a":0,"k":[0,0],"ix":1},"s":{"a":0,"k":[100,100],"ix":3},"r":{"a":0,"k":0,"ix":6},"o":{"a":0,"k":100,"ix":7},"sk":{"a":0,"k":0,"ix":4},"sa":{"a":0,"k":0,"ix":5},"nm":"Transform"}],"nm":"Group 1","np":2,"cix":2,"bm":0,"ix":1,"mn":"ADBE Vector Group","hd":false},{"ty":"gr","it":[{"ind":0,"ty":"sh","ix":1,"ks":{"a":0,"k":{"i":[[0,0],[1.565,0.376],[1.734,1.309],[10.117,0],[0.337,-0.007],[0,0],[0,0]],"o":[[-1.499,-0.531],[-1.528,-1.54],[-8.064,-6.091],[-0.338,0],[0,0],[0,0],[0,0]],"v":[[19.463,-35.306],[14.864,-36.67],[9.966,-40.953],[-17.823,-50.263],[-18.834,-50.243],[-23.066,50.263],[23.066,50.263]],"c":true},"ix":2},"nm":"Path 1","mn":"ADBE Vector Shape - Group","hd":false},{"ty":"fl","c":{"a":0,"k":[0.57647061348,0.698039233685,0.956862747669,1],"ix":4},"o":{"a":0,"k":100,"ix":5},"r":1,"bm":0,"nm":"Fill 1","mn":"ADBE Vector Graphic - Fill","hd":false},{"ty":"tr","p":{"a":0,"k":[316.855,371.937],"ix":2},"a":{"a":0,"k":[0,0],"ix":1},"s":{"a":0,"k":[100,100],"ix":3},"r":{"a":0,"k":0,"ix":6},"o":{"a":0,"k":100,"ix":7},"sk":{"a":0,"k":0,"ix":4},"sa":{"a":0,"k":0,"ix":5},"nm":"Transform"}],"nm":"Group 2","np":2,"cix":2,"bm":0,"ix":2,"mn":"ADBE Vector Group","hd":false},{"ty":"gr","it":[{"ind":0,"ty":"sh","ix":1,"ks":{"a":0,"k":{"i":[[0,0],[0,0],[0,0],[0,0]],"o":[[0,0],[0,0],[0,0],[0,0]],"v":[[-23.066,120.122],[23.066,120.122],[12.951,-120.122],[-12.951,-120.122]],"c":true},"ix":2},"nm":"Path 1","mn":"ADBE Vector Shape - Group","hd":false},{"ty":"fl","c":{"a":0,"k":[0.823529422283,0.86274510622,0.992156863213,1],"ix":4},"o":{"a":0,"k":100,"ix":5},"r":1,"bm":0,"nm":"Fill 1","mn":"ADBE Vector Graphic - Fill","hd":false},{"ty":"tr","p":{"a":0,"k":[316.855,302.078],"ix":2},"a":{"a":0,"k":[0,0],"ix":1},"s":{"a":0,"k":[100,100],"ix":3},"r":{"a":0,"k":0,"ix":6},"o":{"a":0,"k":100,"ix":7},"sk":{"a":0,"k":0,"ix":4},"sa":{"a":0,"k":0,"ix":5},"nm":"Transform"}],"nm":"Group 3","np":2,"cix":2,"bm":0,"ix":3,"mn":"ADBE Vector Group","hd":false},{"ty":"gr","it":[{"ind":0,"ty":"sh","ix":1,"ks":{"a":0,"k":{"i":[[0,0],[0,8.403],[-6.87,0.906],[0,1.804],[-8.403,0],[-1.223,-0.317],[-6.878,0],[-1.883,-6.264],[-1.322,0],[0,-8.403],[0.576,-1.606],[0,-7.433],[8.403,0]],"o":[[-8.403,0],[0,-7.433],[-0.576,-1.606],[0,-8.403],[1.322,0],[1.883,-6.264],[6.877,0],[1.223,-0.317],[8.403,0],[0,1.804],[7.046,1.329],[0,8.403],[0,0]],"v":[[-29.882,30.429],[-45.097,15.215],[-32.719,0.268],[-33.611,-4.872],[-18.397,-20.087],[-14.57,-19.601],[0,-30.429],[14.57,-19.601],[18.397,-20.087],[33.611,-4.872],[32.719,0.268],[45.097,15.215],[29.882,30.429]],"c":true},"ix":2},"nm":"Path 1","mn":"ADBE Vector Shape - Group","hd":false},{"ty":"fl","c":{"a":0,"k":[0.568627476692,0.717647075653,0.023529412225,1],"ix":4},"o":{"a":0,"k":100,"ix":5},"r":1,"bm":0,"nm":"Fill 1","mn":"ADBE Vector Graphic - Fill","hd":false},{"ty":"tr","p":{"a":0,"k":[351.762,391.771],"ix":2},"a":{"a":0,"k":[0,0],"ix":1},"s":{"a":0,"k":[100,100],"ix":3},"r":{"a":0,"k":0,"ix":6},"o":{"a":0,"k":100,"ix":7},"sk":{"a":0,"k":0,"ix":4},"sa":{"a":0,"k":0,"ix":5},"nm":"Transform"}],"nm":"Group 4","np":2,"cix":2,"bm":0,"ix":4,"mn":"ADBE Vector Group","hd":false}],"ip":0,"op":75,"st":0,"ct":1,"bm":0},{"ddd":0,"ind":9,"ty":4,"nm":"mill-L","sr":1,"ks":{"o":{"a":0,"k":100,"ix":11},"r":{"a":1,"k":[{"i":{"x":[0.42],"y":[1]},"o":{"x":[0.58],"y":[0]},"t":5,"s":[0]},{"t":46,"s":[360]}],"ix":10},"p":{"a":0,"k":[175.214,264.074,0],"ix":2,"l":2},"a":{"a":0,"k":[175.214,264.074,0],"ix":1,"l":2},"s":{"a":0,"k":[100,100,100],"ix":6,"l":2}},"ao":0,"shapes":[{"ty":"gr","it":[{"ind":0,"ty":"sh","ix":1,"ks":{"a":0,"k":{"i":[[0,-8.543],[-8.543,0],[0,8.543],[8.543,0]],"o":[[0,8.543],[8.543,0],[0,-8.543],[-8.543,0]],"v":[[-15.469,0],[0,15.469],[15.469,0],[0,-15.469]],"c":true},"ix":2},"nm":"Path 1","mn":"ADBE Vector Shape - Group","hd":false},{"ty":"st","c":{"a":0,"k":[0.20000000298,0.800000011921,0.800000011921,1],"ix":3,"x":"var $bm_rt;\n$bm_rt = thisComp.layer('Main Stroke width - Color Ctrl').effect('Base Color')('Color');"},"o":{"a":0,"k":100,"ix":4},"w":{"a":0,"k":16,"ix":5,"x":"var $bm_rt;\n$bm_rt = thisComp.layer('Main Stroke width - Color Ctrl').effect('Stroke width')('Slider');"},"lc":2,"lj":2,"bm":0,"nm":"Stroke 1","mn":"ADBE Vector Graphic - Stroke","hd":false},{"ty":"tr","p":{"a":0,"k":[175.214,264.027],"ix":2},"a":{"a":0,"k":[0,0],"ix":1},"s":{"a":0,"k":[100,100],"ix":3},"r":{"a":0,"k":0,"ix":6},"o":{"a":0,"k":100,"ix":7},"sk":{"a":0,"k":0,"ix":4},"sa":{"a":0,"k":0,"ix":5},"nm":"Transform"}],"nm":"Group 1","np":2,"cix":2,"bm":0,"ix":1,"mn":"ADBE Vector Group","hd":false},{"ty":"gr","it":[{"ind":0,"ty":"sh","ix":1,"ks":{"a":0,"k":{"i":[[0,0],[0,0],[10.028,-10.575],[0,0],[1.386,-7.405],[0,0],[0,0],[-7.326,1.756],[0,0],[-10.678,9.918],[0,0]],"o":[[0,0],[-13.928,4.289],[0,0],[-5.184,5.466],[0,0],[0,0],[7.105,2.502],[0,0],[14.172,-3.397],[0,0],[0,0]],"v":[[26.789,-27.093],[9.442,-21.751],[-27.101,0.922],[-27.101,0.922],[-37.165,20.641],[-37.757,23.803],[-34.722,24.872],[-12.614,26.016],[-12.614,26.015],[25.293,5.705],[37.757,-5.871]],"c":false},"ix":2},"nm":"Path 1","mn":"ADBE Vector Shape - Group","hd":false},{"ty":"st","c":{"a":0,"k":[0.20000000298,0.800000011921,0.800000011921,1],"ix":3,"x":"var $bm_rt;\n$bm_rt = thisComp.layer('Main Stroke width - Color Ctrl').effect('Base Color')('Color');"},"o":{"a":0,"k":100,"ix":4},"w":{"a":0,"k":16,"ix":5,"x":"var $bm_rt;\n$bm_rt = thisComp.layer('Main Stroke width - Color Ctrl').effect('Stroke width')('Slider');"},"lc":2,"lj":2,"bm":0,"nm":"Stroke 1","mn":"ADBE Vector Graphic - Stroke","hd":false},{"ty":"tr","p":{"a":0,"k":[132.955,286.421],"ix":2},"a":{"a":0,"k":[0,0],"ix":1},"s":{"a":0,"k":[100,100],"ix":3},"r":{"a":0,"k":0,"ix":6},"o":{"a":0,"k":100,"ix":7},"sk":{"a":0,"k":0,"ix":4},"sa":{"a":0,"k":0,"ix":5},"nm":"Transform"}],"nm":"Group 2","np":2,"cix":2,"bm":0,"ix":2,"mn":"ADBE Vector Group","hd":false},{"ty":"gr","it":[{"ind":0,"ty":"sh","ix":1,"ks":{"a":0,"k":{"i":[[0,0],[0,0],[-14.172,-3.397],[0,0],[-7.105,2.502],[0,0],[0,0],[5.184,5.466],[0,0],[13.928,4.289],[0,0]],"o":[[0,0],[10.678,9.918],[0,0],[7.326,1.756],[0,0],[0,0],[-1.386,-7.405],[0,0],[-10.028,-10.575],[0,0],[0,0]],"v":[[-38.06,-6.435],[-24.99,5.705],[12.918,26.016],[12.918,26.016],[35.026,24.872],[38.06,23.803],[37.469,20.641],[27.405,0.922],[27.405,0.922],[-9.138,-21.751],[-26.486,-27.093]],"c":false},"ix":2},"nm":"Path 1","mn":"ADBE Vector Shape - Group","hd":false},{"ty":"st","c":{"a":0,"k":[0.20000000298,0.800000011921,0.800000011921,1],"ix":3,"x":"var $bm_rt;\n$bm_rt = thisComp.layer('Main Stroke width - Color Ctrl').effect('Base Color')('Color');"},"o":{"a":0,"k":100,"ix":4},"w":{"a":0,"k":16,"ix":5,"x":"var $bm_rt;\n$bm_rt = thisComp.layer('Main Stroke width - Color Ctrl').effect('Stroke width')('Slider');"},"lc":2,"lj":2,"bm":0,"nm":"Stroke 1","mn":"ADBE Vector Graphic - Stroke","hd":false},{"ty":"tr","p":{"a":0,"k":[217.169,286.421],"ix":2},"a":{"a":0,"k":[0,0],"ix":1},"s":{"a":0,"k":[100,100],"ix":3},"r":{"a":0,"k":0,"ix":6},"o":{"a":0,"k":100,"ix":7},"sk":{"a":0,"k":0,"ix":4},"sa":{"a":0,"k":0,"ix":5},"nm":"Transform"}],"nm":"Group 3","np":2,"cix":2,"bm":0,"ix":3,"mn":"ADBE Vector Group","hd":false},{"ty":"gr","it":[{"ind":0,"ty":"sh","ix":1,"ks":{"a":0,"k":{"i":[[0,0],[0,0],[4.144,13.972],[0,0],[5.72,4.902],[0,0],[0,0],[2.142,-7.222],[0,0],[-3.25,-14.207],[0,0]],"o":[[0,0],[3.25,-14.207],[0,0],[-2.142,-7.222],[0,0],[0,0],[-5.72,4.902],[0,0],[-4.144,13.972],[0,0],[0,0]],"v":[[11.981,40.051],[15.852,23.133],[14.487,-19.851],[14.487,-19.851],[2.443,-38.426],[0,-40.519],[-2.443,-38.426],[-14.487,-19.851],[-14.487,-19.851],[-15.852,23.133],[-11.874,40.519]],"c":false},"ix":2},"nm":"Path 1","mn":"ADBE Vector Shape - Group","hd":false},{"ty":"st","c":{"a":0,"k":[0.20000000298,0.800000011921,0.800000011921,1],"ix":3,"x":"var $bm_rt;\n$bm_rt = thisComp.layer('Main Stroke width - Color Ctrl').effect('Base Color')('Color');"},"o":{"a":0,"k":100,"ix":4},"w":{"a":0,"k":16,"ix":5,"x":"var $bm_rt;\n$bm_rt = thisComp.layer('Main Stroke width - Color Ctrl').effect('Stroke width')('Slider');"},"lc":2,"lj":2,"bm":0,"nm":"Stroke 1","mn":"ADBE Vector Graphic - Stroke","hd":false},{"ty":"tr","p":{"a":0,"k":[175.214,212.153],"ix":2},"a":{"a":0,"k":[0,0],"ix":1},"s":{"a":0,"k":[100,100],"ix":3},"r":{"a":0,"k":0,"ix":6},"o":{"a":0,"k":100,"ix":7},"sk":{"a":0,"k":0,"ix":4},"sa":{"a":0,"k":0,"ix":5},"nm":"Transform"}],"nm":"Group 4","np":2,"cix":2,"bm":0,"ix":4,"mn":"ADBE Vector Group","hd":false}],"ip":0,"op":75,"st":0,"ct":1,"bm":0},{"ddd":0,"ind":10,"ty":4,"nm":"mill-L","parent":9,"sr":1,"ks":{"o":{"a":0,"k":100,"ix":11},"r":{"a":0,"k":0,"ix":10},"p":{"a":0,"k":[174.908,242.543,0],"ix":2,"l":2},"a":{"a":0,"k":[174.908,242.543,0],"ix":1,"l":2},"s":{"a":0,"k":[100,100,100],"ix":6,"l":2}},"ao":0,"shapes":[{"ty":"gr","it":[{"ind":0,"ty":"sh","ix":1,"ks":{"a":0,"k":{"i":[[0,-8.578],[-8.578,0],[0,8.578],[8.578,0]],"o":[[0,8.578],[8.578,0],[0,-8.578],[-8.578,0]],"v":[[-15.532,0],[0,15.532],[15.532,0],[0,-15.532]],"c":true},"ix":2},"nm":"Path 1","mn":"ADBE Vector Shape - Group","hd":false},{"ty":"fl","c":{"a":0,"k":[0.57647061348,0.698039233685,0.956862747669,1],"ix":4},"o":{"a":0,"k":100,"ix":5},"r":1,"bm":0,"nm":"Fill 1","mn":"ADBE Vector Graphic - Fill","hd":false},{"ty":"tr","p":{"a":0,"k":[174.908,264.085],"ix":2},"a":{"a":0,"k":[0,0],"ix":1},"s":{"a":0,"k":[100,100],"ix":3},"r":{"a":0,"k":0,"ix":6},"o":{"a":0,"k":100,"ix":7},"sk":{"a":0,"k":0,"ix":4},"sa":{"a":0,"k":0,"ix":5},"nm":"Transform"}],"nm":"Group 1","np":2,"cix":2,"bm":0,"ix":1,"mn":"ADBE Vector Group","hd":false},{"ty":"gr","it":[{"ind":0,"ty":"sh","ix":1,"ks":{"a":0,"k":{"i":[[0,0],[3.347,-1.53],[-9.698,-7.074],[-2.707,2.514],[0,0],[0,0]],"o":[[-3.539,1.09],[1.32,12.552],[2.991,-2.129],[0,0],[0,0],[0,0]],"v":[[-10.453,-14.191],[-20.792,-10.252],[-3.095,20.347],[5.464,13.377],[20.792,-0.859],[9.54,-20.347]],"c":true},"ix":2},"nm":"Path 1","mn":"ADBE Vector Shape - Group","hd":false},{"ty":"fl","c":{"a":0,"k":[0.992156863213,0.560784339905,0.003921568859,1],"ix":4},"o":{"a":0,"k":100,"ix":5},"r":1,"bm":0,"nm":"Fill 1","mn":"ADBE Vector Graphic - Fill","hd":false},{"ty":"tr","p":{"a":0,"k":[152.411,278.921],"ix":2},"a":{"a":0,"k":[0,0],"ix":1},"s":{"a":0,"k":[100,100],"ix":3},"r":{"a":0,"k":0,"ix":6},"o":{"a":0,"k":100,"ix":7},"sk":{"a":0,"k":0,"ix":4},"sa":{"a":0,"k":0,"ix":5},"nm":"Transform"}],"nm":"Group 2","np":2,"cix":2,"bm":0,"ix":2,"mn":"ADBE Vector Group","hd":false},{"ty":"gr","it":[{"ind":0,"ty":"sh","ix":1,"ks":{"a":0,"k":{"i":[[0,0],[0,0],[0,0],[10.069,-10.618],[0,0],[1.391,-7.435],[0,0],[0,0],[-7.356,1.763],[0,0],[-10.722,9.958]],"o":[[0,0],[0,0],[-13.985,4.306],[0,0],[-5.205,5.489],[0,0],[0,0],[7.134,2.513],[0,0],[14.23,-3.411],[0,0]],"v":[[39.318,-8.112],[28.067,-27.6],[8.073,-21.443],[-28.619,1.323],[-28.619,1.323],[-38.724,21.121],[-39.318,24.297],[-36.271,25.37],[-14.073,26.518],[-14.072,26.518],[23.99,6.125]],"c":true},"ix":2},"nm":"Path 1","mn":"ADBE Vector Shape - Group","hd":false},{"ty":"fl","c":{"a":0,"k":[0.992156863213,0.796078443527,0.313725501299,1],"ix":4},"o":{"a":0,"k":100,"ix":5},"r":1,"bm":0,"nm":"Fill 1","mn":"ADBE Vector Graphic - Fill","hd":false},{"ty":"tr","p":{"a":0,"k":[133.885,286.173],"ix":2},"a":{"a":0,"k":[0,0],"ix":1},"s":{"a":0,"k":[100,100],"ix":3},"r":{"a":0,"k":0,"ix":6},"o":{"a":0,"k":100,"ix":7},"sk":{"a":0,"k":0,"ix":4},"sa":{"a":0,"k":0,"ix":5},"nm":"Transform"}],"nm":"Group 3","np":2,"cix":2,"bm":0,"ix":3,"mn":"ADBE Vector Group","hd":false},{"ty":"gr","it":[{"ind":0,"ty":"sh","ix":1,"ks":{"a":0,"k":{"i":[[3.539,1.09],[0,0],[0,0],[0,0],[-2.991,-2.129],[-1.32,12.552]],"o":[[0,0],[0,0],[0,0],[2.707,2.514],[9.698,-7.074],[-3.347,-1.53]],"v":[[10.453,-14.191],[-9.54,-20.347],[-20.792,-0.859],[-5.464,13.377],[3.095,20.347],[20.792,-10.252]],"c":true},"ix":2},"nm":"Path 1","mn":"ADBE Vector Shape - Group","hd":false},{"ty":"fl","c":{"a":0,"k":[0.992156863213,0.560784339905,0.003921568859,1],"ix":4},"o":{"a":0,"k":100,"ix":5},"r":1,"bm":0,"nm":"Fill 1","mn":"ADBE Vector Graphic - Fill","hd":false},{"ty":"tr","p":{"a":0,"k":[197.406,278.921],"ix":2},"a":{"a":0,"k":[0,0],"ix":1},"s":{"a":0,"k":[100,100],"ix":3},"r":{"a":0,"k":0,"ix":6},"o":{"a":0,"k":100,"ix":7},"sk":{"a":0,"k":0,"ix":4},"sa":{"a":0,"k":0,"ix":5},"nm":"Transform"}],"nm":"Group 4","np":2,"cix":2,"bm":0,"ix":4,"mn":"ADBE Vector Group","hd":false},{"ty":"gr","it":[{"ind":0,"ty":"sh","ix":1,"ks":{"a":0,"k":{"i":[[0,0],[0,0],[0,0],[-14.23,-3.411],[0,0],[-7.134,2.513],[0,0],[0,0],[5.205,5.489],[0,0],[13.985,4.306]],"o":[[0,0],[0,0],[10.722,9.958],[0,0],[7.356,1.763],[0,0],[0,0],[-1.391,-7.435],[0,0],[-10.069,-10.618],[0,0]],"v":[[-28.067,-27.6],[-39.318,-8.112],[-23.99,6.125],[14.072,26.518],[14.073,26.518],[36.271,25.37],[39.318,24.297],[38.724,21.121],[28.619,1.323],[28.619,1.323],[-8.073,-21.443]],"c":true},"ix":2},"nm":"Path 1","mn":"ADBE Vector Shape - Group","hd":false},{"ty":"fl","c":{"a":0,"k":[0.992156863213,0.796078443527,0.313725501299,1],"ix":4},"o":{"a":0,"k":100,"ix":5},"r":1,"bm":0,"nm":"Fill 1","mn":"ADBE Vector Graphic - Fill","hd":false},{"ty":"tr","p":{"a":0,"k":[215.932,286.173],"ix":2},"a":{"a":0,"k":[0,0],"ix":1},"s":{"a":0,"k":[100,100],"ix":3},"r":{"a":0,"k":0,"ix":6},"o":{"a":0,"k":100,"ix":7},"sk":{"a":0,"k":0,"ix":4},"sa":{"a":0,"k":0,"ix":5},"nm":"Transform"}],"nm":"Group 5","np":2,"cix":2,"bm":0,"ix":5,"mn":"ADBE Vector Group","hd":false},{"ty":"gr","it":[{"ind":0,"ty":"sh","ix":1,"ks":{"a":0,"k":{"i":[[6.291,0],[5.405,-2.412],[-0.825,-3.606],[0,0],[0,0],[0,0],[-0.348,3.659]],"o":[[-6.291,0],[0.348,3.659],[0,0],[0,0],[0,0],[0.825,-3.606],[-5.405,-2.412]],"v":[[0,-17.533],[-17.674,-13.769],[-15.917,-2.86],[-11.251,17.533],[11.251,17.533],[15.917,-2.86],[17.674,-13.769]],"c":true},"ix":2},"nm":"Path 1","mn":"ADBE Vector Shape - Group","hd":false},{"ty":"fl","c":{"a":0,"k":[0.992156863213,0.560784339905,0.003921568859,1],"ix":4},"o":{"a":0,"k":100,"ix":5},"r":1,"bm":0,"nm":"Fill 1","mn":"ADBE Vector Graphic - Fill","hd":false},{"ty":"tr","p":{"a":0,"k":[174.908,238.085],"ix":2},"a":{"a":0,"k":[0,0],"ix":1},"s":{"a":0,"k":[100,100],"ix":3},"r":{"a":0,"k":0,"ix":6},"o":{"a":0,"k":100,"ix":7},"sk":{"a":0,"k":0,"ix":4},"sa":{"a":0,"k":0,"ix":5},"nm":"Transform"}],"nm":"Group 6","np":2,"cix":2,"bm":0,"ix":6,"mn":"ADBE Vector Group","hd":false},{"ty":"gr","it":[{"ind":0,"ty":"sh","ix":1,"ks":{"a":0,"k":{"i":[[0,0],[0,0],[0,0],[4.161,14.029],[0,0],[5.743,4.922],[0,0],[0,0],[2.151,-7.252],[0,0],[-3.263,-14.265]],"o":[[0,0],[0,0],[3.263,-14.265],[0,0],[-2.151,-7.252],[0,0],[0,0],[-5.743,4.922],[0,0],[-4.161,14.029],[0,0]],"v":[[-11.251,42.152],[11.251,42.152],[15.916,21.759],[14.547,-21.4],[14.547,-21.4],[2.453,-40.05],[0,-42.152],[-2.453,-40.05],[-14.547,-21.4],[-14.547,-21.4],[-15.916,21.759]],"c":true},"ix":2},"nm":"Path 1","mn":"ADBE Vector Shape - Group","hd":false},{"ty":"fl","c":{"a":0,"k":[0.992156863213,0.796078443527,0.313725501299,1],"ix":4},"o":{"a":0,"k":100,"ix":5},"r":1,"bm":0,"nm":"Fill 1","mn":"ADBE Vector Graphic - Fill","hd":false},{"ty":"tr","p":{"a":0,"k":[174.908,213.466],"ix":2},"a":{"a":0,"k":[0,0],"ix":1},"s":{"a":0,"k":[100,100],"ix":3},"r":{"a":0,"k":0,"ix":6},"o":{"a":0,"k":100,"ix":7},"sk":{"a":0,"k":0,"ix":4},"sa":{"a":0,"k":0,"ix":5},"nm":"Transform"}],"nm":"Group 7","np":2,"cix":2,"bm":0,"ix":7,"mn":"ADBE Vector Group","hd":false}],"ip":0,"op":75,"st":0,"ct":1,"bm":0},{"ddd":0,"ind":11,"ty":4,"nm":"left","sr":1,"ks":{"o":{"a":0,"k":100,"ix":11},"r":{"a":0,"k":0,"ix":10},"p":{"a":0,"k":[145.762,349.598,0],"ix":2,"l":2},"a":{"a":0,"k":[145.762,349.598,0],"ix":1,"l":2},"s":{"a":0,"k":[100,100,100],"ix":6,"l":2}},"ao":0,"shapes":[{"ty":"gr","it":[{"ind":0,"ty":"sh","ix":1,"ks":{"a":0,"k":{"i":[[0,0],[0,0]],"o":[[0,0],[0,0]],"v":[[3.997,71.307],[-3.997,-71.307]],"c":false},"ix":2},"nm":"Path 1","mn":"ADBE Vector Shape - Group","hd":false},{"ty":"st","c":{"a":0,"k":[0,0,0,1],"ix":3,"x":"var $bm_rt;\n$bm_rt = thisComp.layer('Main Stroke width - Color Ctrl').effect('Base Color')('Color');"},"o":{"a":0,"k":100,"ix":4},"w":{"a":0,"k":16,"ix":5,"x":"var $bm_rt;\n$bm_rt = thisComp.layer('Main Stroke width - Color Ctrl').effect('Stroke width')('Slider');"},"lc":2,"lj":2,"bm":0,"nm":"Stroke 1","mn":"ADBE Vector Graphic - Stroke","hd":false},{"ty":"tr","p":{"a":0,"k":[191.171,349.002],"ix":2},"a":{"a":0,"k":[0,0],"ix":1},"s":{"a":0,"k":[100,100],"ix":3},"r":{"a":0,"k":0,"ix":6},"o":{"a":0,"k":100,"ix":7},"sk":{"a":0,"k":0,"ix":4},"sa":{"a":0,"k":0,"ix":5},"nm":"Transform"}],"nm":"Group 1","np":2,"cix":2,"bm":0,"ix":1,"mn":"ADBE Vector Group","hd":false},{"ty":"gr","it":[{"ind":0,"ty":"sh","ix":1,"ks":{"a":0,"k":{"i":[[0,0],[0,0]],"o":[[0,0],[0,0]],"v":[[3.833,-70.639],[-3.833,70.639]],"c":false},"ix":2},"nm":"Path 1","mn":"ADBE Vector Shape - Group","hd":false},{"ty":"st","c":{"a":0,"k":[0,0,0,1],"ix":3,"x":"var $bm_rt;\n$bm_rt = thisComp.layer('Main Stroke width - Color Ctrl').effect('Base Color')('Color');"},"o":{"a":0,"k":100,"ix":4},"w":{"a":0,"k":16,"ix":5,"x":"var $bm_rt;\n$bm_rt = thisComp.layer('Main Stroke width - Color Ctrl').effect('Stroke width')('Slider');"},"lc":2,"lj":2,"bm":0,"nm":"Stroke 1","mn":"ADBE Vector Graphic - Stroke","hd":false},{"ty":"tr","p":{"a":0,"k":[159.08,349.9],"ix":2},"a":{"a":0,"k":[0,0],"ix":1},"s":{"a":0,"k":[100,100],"ix":3},"r":{"a":0,"k":0,"ix":6},"o":{"a":0,"k":100,"ix":7},"sk":{"a":0,"k":0,"ix":4},"sa":{"a":0,"k":0,"ix":5},"nm":"Transform"}],"nm":"Group 2","np":2,"cix":2,"bm":0,"ix":2,"mn":"ADBE Vector Group","hd":false},{"ty":"gr","it":[{"ind":0,"ty":"sh","ix":1,"ks":{"a":0,"k":{"i":[[0,0],[0,7.757],[-6.342,0.836],[0,1.666],[-7.757,0],[-1.129,-0.292],[-6.349,0],[-1.739,-5.783],[-1.22,0],[-0.718,-0.113]],"o":[[-7.757,0],[0,-6.862],[-0.532,-1.483],[0,-7.757],[1.22,0],[1.739,-5.783],[6.349,0],[1.129,-0.292],[0.75,0],[0,0]],"v":[[-16.365,28.092],[-30.411,14.046],[-18.984,0.248],[-19.807,-4.498],[-5.761,-18.544],[-2.228,-18.095],[11.223,-28.092],[24.673,-18.095],[28.206,-18.544],[30.411,-18.372]],"c":false},"ix":2},"nm":"Path 1","mn":"ADBE Vector Shape - Group","hd":false},{"ty":"st","c":{"a":0,"k":[0.20000000298,0.800000011921,0.800000011921,1],"ix":3,"x":"var $bm_rt;\n$bm_rt = thisComp.layer('Main Stroke width - Color Ctrl').effect('Base Color')('Color');"},"o":{"a":0,"k":100,"ix":4},"w":{"a":0,"k":16,"ix":5,"x":"var $bm_rt;\n$bm_rt = thisComp.layer('Main Stroke width - Color Ctrl').effect('Stroke width')('Slider');"},"lc":2,"lj":2,"bm":0,"nm":"Stroke 1","mn":"ADBE Vector Graphic - Stroke","hd":false},{"ty":"tr","p":{"a":0,"k":[126.768,393.408],"ix":2},"a":{"a":0,"k":[0,0],"ix":1},"s":{"a":0,"k":[100,100],"ix":3},"r":{"a":0,"k":0,"ix":6},"o":{"a":0,"k":100,"ix":7},"sk":{"a":0,"k":0,"ix":4},"sa":{"a":0,"k":0,"ix":5},"nm":"Transform"}],"nm":"Group 3","np":2,"cix":2,"bm":0,"ix":3,"mn":"ADBE Vector Group","hd":false}],"ip":0,"op":75,"st":0,"ct":1,"bm":0},{"ddd":0,"ind":12,"ty":4,"nm":"left","sr":1,"ks":{"o":{"a":0,"k":100,"ix":11},"r":{"a":0,"k":0,"ix":10},"p":{"a":0,"k":[145.37,342.141,0],"ix":2,"l":2},"a":{"a":0,"k":[145.37,342.141,0],"ix":1,"l":2},"s":{"a":0,"k":[100,100,100],"ix":6,"l":2}},"ao":0,"shapes":[{"ty":"gr","it":[{"ind":0,"ty":"sh","ix":1,"ks":{"a":0,"k":{"i":[[0,0],[0,0],[0,0],[0,0]],"o":[[0,0],[0,0],[0,0],[0,0]],"v":[[-20.101,80.059],[20.101,80.059],[11.286,-80.059],[-11.286,-80.059]],"c":true},"ix":2},"nm":"Path 1","mn":"ADBE Vector Shape - Group","hd":false},{"ty":"fl","c":{"a":0,"k":[0.823529422283,0.86274510622,0.992156863213,1],"ix":4},"o":{"a":0,"k":100,"ix":5},"r":1,"bm":0,"nm":"Fill 1","mn":"ADBE Vector Graphic - Fill","hd":false},{"ty":"tr","p":{"a":0,"k":[174.908,342.141],"ix":2},"a":{"a":0,"k":[0,0],"ix":1},"s":{"a":0,"k":[100,100],"ix":3},"r":{"a":0,"k":0,"ix":6},"o":{"a":0,"k":100,"ix":7},"sk":{"a":0,"k":0,"ix":4},"sa":{"a":0,"k":0,"ix":5},"nm":"Transform"}],"nm":"Group 1","np":2,"cix":2,"bm":0,"ix":1,"mn":"ADBE Vector Group","hd":false},{"ty":"gr","it":[{"ind":0,"ty":"sh","ix":1,"ks":{"a":0,"k":{"i":[[0,0],[0,7.789],[-6.368,0.84],[0,1.673],[-7.789,0],[-1.133,-0.294],[-6.375,0],[-1.746,-5.807],[-1.225,0],[0,-7.789],[0.534,-1.489],[0,-6.89],[7.789,0]],"o":[[-7.789,0],[0,-6.89],[-0.534,-1.489],[0,-7.789],[1.225,0],[1.746,-5.807],[6.375,0],[1.133,-0.294],[7.789,0],[0,1.673],[6.532,1.232],[0,7.789],[0,0]],"v":[[-27.7,28.207],[-41.803,14.103],[-30.329,0.249],[-31.157,-4.516],[-17.053,-18.62],[-13.506,-18.169],[0,-28.207],[13.506,-18.169],[17.053,-18.62],[31.157,-4.516],[30.329,0.249],[41.803,14.103],[27.7,28.207]],"c":true},"ix":2},"nm":"Path 1","mn":"ADBE Vector Shape - Group","hd":false},{"ty":"fl","c":{"a":0,"k":[0.694117665291,0.850980401039,0.321568638086,1],"ix":4},"o":{"a":0,"k":100,"ix":5},"r":1,"bm":0,"nm":"Fill 1","mn":"ADBE Vector Graphic - Fill","hd":false},{"ty":"tr","p":{"a":0,"k":[137.534,393.993],"ix":2},"a":{"a":0,"k":[0,0],"ix":1},"s":{"a":0,"k":[100,100],"ix":3},"r":{"a":0,"k":0,"ix":6},"o":{"a":0,"k":100,"ix":7},"sk":{"a":0,"k":0,"ix":4},"sa":{"a":0,"k":0,"ix":5},"nm":"Transform"}],"nm":"Group 2","np":2,"cix":2,"bm":0,"ix":2,"mn":"ADBE Vector Group","hd":false}],"ip":0,"op":75,"st":0,"ct":1,"bm":0}],"markers":[]}